[{"title":"Let's Roll","slug":"lets-roll","url":"/post/lets-roll","tags":[{"name":"3D","slug":"3d"}],"description":"Create your First 3D Game in Godot where the user plays as a bouncing ball.","thumbnail":"/illustrations/lets-roll/thumbnail.png","draft":false,"compiledMdx":{"compiledSource":"var c=Object.defineProperty,N=Object.defineProperties;var d=Object.getOwnPropertyDescriptors;var p=Object.getOwnPropertySymbols;var o=Object.prototype.hasOwnProperty,l=Object.prototype.propertyIsEnumerable;var i=(e,n,s)=>n in e?c(e,n,{enumerable:!0,configurable:!0,writable:!0,value:s}):e[n]=s,a=(e,n)=>{for(var s in n||(n={}))o.call(n,s)&&i(e,s,n[s]);if(p)for(var s of p(n))l.call(n,s)&&i(e,s,n[s]);return e},r=(e,n)=>N(e,d(n));var u=typeof require!=\"undefined\"?require:e=>{throw new Error('Dynamic require of \"'+e+'\" is not supported')};var m=(e,n)=>{var s={};for(var t in e)o.call(e,t)&&n.indexOf(t)<0&&(s[t]=e[t]);if(e!=null&&p)for(var t of p(e))n.indexOf(t)<0&&l.call(e,t)&&(s[t]=e[t]);return s};const makeShortcode=e=>function(s){return console.warn(\"Component \"+e+\" was not imported, exported, or provided by MDXProvider as global scope\"),mdx(\"div\",a({},s))},Video=makeShortcode(\"Video\"),Downloads=makeShortcode(\"Downloads\"),layoutProps={},MDXLayout=\"wrapper\";function MDXContent(s){var t=s,{components:e}=t,n=m(t,[\"components\"]);return mdx(MDXLayout,r(a(a({},layoutProps),n),{components:e,mdxType:\"MDXLayout\"}),mdx(\"h1\",a({},{id:\"lets-roll---create-your-first-3d-game-in-godot\"}),mdx(\"a\",a({parentName:\"h1\"},{className:\"header-link\",href:\"#lets-roll---create-your-first-3d-game-in-godot\"}),mdx(\"span\",a({parentName:\"a\"},{className:\"icon icon-link\"}))),\"Let's Roll - Create your First 3D Game in Godot\"),mdx(\"p\",null,\"In this tutorial I will walk you through creating your first 3D game in Godot:\"),mdx(Video,{url:\"https://www.youtube.com/watch?v=bG2EikJ7k3E\",mdxType:\"Video\"}),mdx(\"p\",null,\"(you can try playing it in browser \",mdx(\"a\",a({parentName:\"p\"},{href:\"https://gotm.io/godotacademy/lets-roll\"}),\"here\"),\").\"),mdx(\"h2\",a({},{id:\"prerequisites\"}),mdx(\"a\",a({parentName:\"h2\"},{className:\"header-link\",href:\"#prerequisites\"}),mdx(\"span\",a({parentName:\"a\"},{className:\"icon icon-link\"}))),\"Prerequisites\"),mdx(\"ul\",null,mdx(\"li\",{parentName:\"ul\"},\"You need to understand the \",mdx(\"a\",a({parentName:\"li\"},{href:\"https://www.youtube.com/watch?v=UcdwP1Q2UlU\"}),\"fundamentals of programming\"),\" (if/else, class, function, etc).\"),mdx(\"li\",{parentName:\"ul\"},\"You need to be familiar with \",mdx(\"a\",a({parentName:\"li\"},{href:\"https://docs.godotengine.org/en/stable/getting_started/step_by_step/intro_to_the_editor_interface.html\"}),\"Godot UI\"),\" and some basic concepts like \",mdx(\"a\",a({parentName:\"li\"},{href:\"https://docs.godotengine.org/en/stable/getting_started/step_by_step/scenes_and_nodes.html\"}),\"scenes and nodes\"),\". You need to be able to create and save scenes, add nodes, edit node settings, connect \",mdx(\"a\",a({parentName:\"li\"},{href:\"https://docs.godotengine.org/en/stable/getting_started/step_by_step/signals.html\"}),\"signals\"),\".\")),mdx(\"p\",null,\"If you get confused at any point, just ask questions in our \",mdx(\"a\",a({parentName:\"p\"},{href:\"https://discord.gg/Wbzuk2JP8Y\"}),\"discord server\"),\" or in the \",mdx(\"a\",a({parentName:\"p\"},{href:\"https://www.reddit.com/r/godot/comments/pv11sp/i_wrote_my_first_godot_tutorial_about_making_a/\"}),\"reddit comments\"),\".\"),mdx(\"h2\",a({},{id:\"download-project-files\"}),mdx(\"a\",a({parentName:\"h2\"},{className:\"header-link\",href:\"#download-project-files\"}),mdx(\"span\",a({parentName:\"a\"},{className:\"icon icon-link\"}))),\"Download Project Files\"),mdx(\"p\",null,\"First, download the project files:\"),mdx(\"ul\",null,mdx(\"li\",{parentName:\"ul\"},mdx(\"inlineCode\",{parentName:\"li\"},\"lets-roll-assets.zip\"),\" contains the initial assets you need to build the game (models for the ball and the level). \"),mdx(\"li\",{parentName:\"ul\"},mdx(\"inlineCode\",{parentName:\"li\"},\"lets-roll-final.zip\"),\" contains the completed project you can use as reference if you get stuck at any point.\",mdx(Downloads,{mdxType:\"Downloads\"},{name:\"lets-roll-assets.zip\",url:\"/files/lets-roll/lets-roll-assets.zip\"},{name:\"lets-roll-final.zip\",url:\"/files/lets-roll/lets-roll-final.zip\"}))),mdx(\"h2\",a({},{id:\"create-a-new-project-and-import-the-assets\"}),mdx(\"a\",a({parentName:\"h2\"},{className:\"header-link\",href:\"#create-a-new-project-and-import-the-assets\"}),mdx(\"span\",a({parentName:\"a\"},{className:\"icon icon-link\"}))),\"Create a New Project and Import the Assets\"),mdx(\"p\",null,\"Create a new project:\"),mdx(\"p\",null,mdx(\"img\",a({parentName:\"p\"},{src:\"/illustrations/lets-roll/01-create-new-project.png\",alt:null}))),mdx(\"p\",null,\"Unpack the zip file with the assets, and drag them into the project folder.\"),mdx(\"p\",null,mdx(\"img\",a({parentName:\"p\"},{src:\"/illustrations/lets-roll/02-copy-assets.png\",alt:null}))),mdx(\"h2\",a({},{id:\"creating-the-level-geometry\"}),mdx(\"a\",a({parentName:\"h2\"},{className:\"header-link\",href:\"#creating-the-level-geometry\"}),mdx(\"span\",a({parentName:\"a\"},{className:\"icon icon-link\"}))),\"Creating the Level Geometry\"),mdx(\"h3\",a({},{id:\"convert-block-models-into-mesh-library\"}),mdx(\"a\",a({parentName:\"h3\"},{className:\"header-link\",href:\"#convert-block-models-into-mesh-library\"}),mdx(\"span\",a({parentName:\"a\"},{className:\"icon icon-link\"}))),\"Convert Block Models into Mesh Library\"),mdx(\"p\",null,\"Open \",mdx(\"inlineCode\",{parentName:\"p\"},\"res://assets/models/blocks.gltf\"),\" file. This file was exported from Blender, it contains the block models we will use to build our level. The \",mdx(\"inlineCode\",{parentName:\"p\"},\".gltf\"),' file itself is not editable in Godot, so when you double click on the file, choose \"New Inherited\" - that will create a new Godot scene (in the ',mdx(\"inlineCode\",{parentName:\"p\"},\".tscn\"),\" format) which we can actually edit. Save the newly created scene as \",mdx(\"inlineCode\",{parentName:\"p\"},\"res://assets/models/blocks.tscn\")),mdx(\"p\",null,mdx(\"img\",a({parentName:\"p\"},{src:\"/illustrations/lets-roll/03-blocks-tscn.png\",alt:null}))),mdx(\"p\",null,\"Our goal is to be able to conveniently build game levels out of these blocks. To accomplish that will will use the \",mdx(\"a\",a({parentName:\"p\"},{href:\"https://docs.godotengine.org/en/stable/classes/class_gridmap.html#class-gridmap\"}),\"GridMap\"),\" node - it will help us to place these blocks into the level quickly and interactively. \"),mdx(\"p\",null,\"To be able to use the block models in \",mdx(\"inlineCode\",{parentName:\"p\"},\"GridMap\"),`, we need to convert them into \"Mesh Library\". That's very simple - click `,mdx(\"inlineCode\",{parentName:\"p\"},\"Scene > Convert To > MeshLibrary...\"),\" and save it as \",mdx(\"inlineCode\",{parentName:\"p\"},\"res://assets/models/blocks.meshlib\"),\":\"),mdx(\"p\",null,mdx(\"img\",a({parentName:\"p\"},{src:\"/illustrations/lets-roll/04-convert-to-meshlib.png\",alt:null}))),mdx(\"h3\",a({},{id:\"building-the-level\"}),mdx(\"a\",a({parentName:\"h3\"},{className:\"header-link\",href:\"#building-the-level\"}),mdx(\"span\",a({parentName:\"a\"},{className:\"icon icon-link\"}))),\"Building the Level\"),mdx(\"p\",null,\"Our next step is to use these blocks to build the first level for our game. In the \",mdx(\"inlineCode\",{parentName:\"p\"},\"FileSystem\"),' panel create a new folder called \"Environment\", create a new 3D Scene, name it \"Level01\", and save it in the Environment folder:'),mdx(\"img\",{className:\"narrow\",src:\"/illustrations/lets-roll/05-create-level-scene.png\"}),mdx(\"p\",null,\"Add a \",mdx(\"inlineCode\",{parentName:\"p\"},\"GridMap\"),\" node, and drag the \",mdx(\"inlineCode\",{parentName:\"p\"},\"res://assets/models/blocks.meshlib\"),\" file we've created in the previous section into the \",mdx(\"inlineCode\",{parentName:\"p\"},\"MeshLibrary\"),\" property:\"),mdx(\"p\",null,mdx(\"img\",a({parentName:\"p\"},{src:\"/illustrations/lets-roll/06-gridmap-meshlib-settings.png\",alt:null}))),mdx(\"p\",null,\"Make sure to change the \",mdx(\"inlineCode\",{parentName:\"p\"},\"Cell\"),\" settings to the onces you see in the screenshot:\"),mdx(\"ul\",null,mdx(\"li\",{parentName:\"ul\"},\"Set the Cell Size to 4x4x4 (to make the size of the cell match the size of our block models)\"),mdx(\"li\",{parentName:\"ul\"},\"Un-check CenterX, CenterY, and CenterZ (we don't need our blocks to be automatically centered).\")),mdx(\"p\",null,\"Now you can select the blocks from the list of meshes in the GridMap panel, and build a level out of them:\"),mdx(\"p\",null,mdx(\"img\",a({parentName:\"p\"},{src:\"/illustrations/lets-roll/07-building-a-level.png\",alt:null}))),mdx(\"ul\",null,mdx(\"li\",{parentName:\"ul\"},\"Select the block from the panel and click LMB to place it into the level.\"),mdx(\"li\",{parentName:\"ul\"},\"Use \",mdx(\"inlineCode\",{parentName:\"li\"},\"Q\"),\" and \",mdx(\"inlineCode\",{parentName:\"li\"},\"E\"),\" to lower or raise the construction grid.\"),mdx(\"li\",{parentName:\"ul\"},\"Use \",mdx(\"inlineCode\",{parentName:\"li\"},\"A\"),\", \",mdx(\"inlineCode\",{parentName:\"li\"},\"S\"),\", \",mdx(\"inlineCode\",{parentName:\"li\"},\"D\"),\", \",mdx(\"inlineCode\",{parentName:\"li\"},\"W\"),\" buttons to rotate the blocks however you want (You'll be mostly using \",mdx(\"inlineCode\",{parentName:\"li\"},\"S\"),\" button to rotate the blocks around the Y axis).\"),mdx(\"li\",{parentName:\"ul\"},\"Right click removes the block.\")),mdx(\"p\",null,\"Now we have made a level our ball can roll around in!\"),mdx(\"h2\",a({},{id:\"create-the-ball\"}),mdx(\"a\",a({parentName:\"h2\"},{className:\"header-link\",href:\"#create-the-ball\"}),mdx(\"span\",a({parentName:\"a\"},{className:\"icon icon-link\"}))),\"Create the Ball\"),mdx(\"p\",null,\"Now it's time to make the ball that is going to roll around the level and jump as the player controls it.\"),mdx(\"h3\",a({},{id:\"setting-up-the-ball-scene\"}),mdx(\"a\",a({parentName:\"h3\"},{className:\"header-link\",href:\"#setting-up-the-ball-scene\"}),mdx(\"span\",a({parentName:\"a\"},{className:\"icon icon-link\"}))),\"Setting up the Ball scene\"),mdx(\"p\",null,\"In this section, our goal will be to create the scene for the Ball that can be controlled by the player. It will look like this:\"),mdx(\"p\",null,mdx(\"img\",a({parentName:\"p\"},{src:\"/illustrations/lets-roll/08-ball-scene.png\",alt:null}))),mdx(\"p\",null,\"Ball is a \",mdx(\"inlineCode\",{parentName:\"p\"},\"RigidBody\"),\" node (which means that Godot will automatically calculate and apply physics to it, making the ball bounce and roll). It has a spherical collision shape, and a \",mdx(\"inlineCode\",{parentName:\"p\"},\"Camera\"),` attached to it (that's the camera the player will look at the scene through). We also have a \"FloorCheck\" raycast which points towards the floor - we will use it to determine whether the ball is currently on the floor and allowed to jump.`),mdx(\"p\",null,\"Create a new scene with \",mdx(\"inlineCode\",{parentName:\"p\"},\"RigidBody\"),\" node as its root:\"),mdx(\"p\",null,mdx(\"img\",a({parentName:\"p\"},{src:\"/illustrations/lets-roll/08.1-new-rigid-body.png\",alt:null}))),mdx(\"p\",null,'Rename the node as \"Ball\", and save it to ',mdx(\"inlineCode\",{parentName:\"p\"},\"res://Player/Ball.tscn\")),mdx(\"p\",null,\"From the assets folder drag the \",mdx(\"inlineCode\",{parentName:\"p\"},\"pixar-ball.obj\"),\" model onto the scene and reset its \",mdx(\"inlineCode\",{parentName:\"p\"},\"Transform\"),\" to zero, to place it into the center of the scene.\"),mdx(\"p\",null,\"Assign a new material to the \",mdx(\"inlineCode\",{parentName:\"p\"},\"pixar-ball\"),\" node:\"),mdx(\"img\",{className:\"narrow\",src:\"/illustrations/lets-roll/09-assign-ball-material.png\"}),mdx(\"p\",null,\"From the \",mdx(\"inlineCode\",{parentName:\"p\"},\"res://assets/textures\"),\" folder drag the \",mdx(\"inlineCode\",{parentName:\"p\"},\"pixar-ball.png\"),\" texture into the material's albedo texture slot:\"),mdx(\"img\",{className:\"narrow\",src:\"/illustrations/lets-roll/10-assign-ball-texture.png\"}),mdx(\"p\",null,\"Set the material's \",mdx(\"inlineCode\",{parentName:\"p\"},\"roughness\"),\" to 0.4, which will add a nice highlight to the ball making it shinier.\"),mdx(\"p\",null,\"Add a new \",mdx(\"inlineCode\",{parentName:\"p\"},\"CollisionShape\"),\" node under the \",mdx(\"inlineCode\",{parentName:\"p\"},\"Ball\"),\" node, and under \",mdx(\"inlineCode\",{parentName:\"p\"},\"Shape\"),\" property create \",mdx(\"inlineCode\",{parentName:\"p\"},\"New Sphere Shape\"),\":\"),mdx(\"p\",null,mdx(\"img\",a({parentName:\"p\"},{src:\"/illustrations/lets-roll/10.1-add-collision-shape.png\",alt:null}))),mdx(\"p\",null,\"CollisionShape represents a simplified shape of the Ball model, Godot uses it when it simulates the physics to allow our ball to actually interact with other physics objects (bounce off the floor for example).\"),mdx(\"h3\",a({},{id:\"adding-camera-rig\"}),mdx(\"a\",a({parentName:\"h3\"},{className:\"header-link\",href:\"#adding-camera-rig\"}),mdx(\"span\",a({parentName:\"a\"},{className:\"icon icon-link\"}))),\"Adding Camera Rig\"),mdx(\"p\",null,\"Now we want to have a camera attached to the Ball, so that as the ball moves, the camera moves along with it.\"),mdx(\"p\",null,\"Create a new \",mdx(\"inlineCode\",{parentName:\"p\"},\"Position3D\"),' node under the \"Ball\", and name it \"CameraRig\". Underneath the \"CameraRig\" add a ',mdx(\"inlineCode\",{parentName:\"p\"},\"Camera\"),\" node:\"),mdx(\"p\",null,mdx(\"img\",a({parentName:\"p\"},{src:\"/illustrations/lets-roll/11.0-camera-rig.png\",alt:null}))),mdx(\"p\",null,\"Set Camera's Translation to \",mdx(\"inlineCode\",{parentName:\"p\"},\"(0, 2.85, 3.5)\"),\" and Rotation X to \",mdx(\"inlineCode\",{parentName:\"p\"},\"-30\"),\", so that camera is looking at the ball from behind and above:\"),mdx(\"p\",null,mdx(\"img\",a({parentName:\"p\"},{src:\"/illustrations/lets-roll/11.1-camera-transform.png\",alt:null}))),mdx(\"p\",null,'We need the \"CameraRig\" node because later on we will write the code that continuously positions \"CameraRig\" right in the middle of the Ball, so that as the ball moves, camera moves with it. The \"Camera\" node is positioned relative to the \"CameraRig\", so that its always looking at the ball from the same distance and angle.'),mdx(\"p\",null,\"Don't forget to save the scene, then add it to the \",mdx(\"inlineCode\",{parentName:\"p\"},\"Level01\"),\" scene (by clicking on the link icon in the Scene panel). Lift the Ball 1 unit up on the Y axis, so that it's resting on the floor. Now if you run the game, you will see the Ball in the middle of our level:\"),mdx(\"p\",null,mdx(\"img\",a({parentName:\"p\"},{src:\"/illustrations/lets-roll/12-ball-and-level-set-up.png\",alt:null}))),mdx(\"h3\",a({},{id:\"movement-code\"}),mdx(\"a\",a({parentName:\"h3\"},{className:\"header-link\",href:\"#movement-code\"}),mdx(\"span\",a({parentName:\"a\"},{className:\"icon icon-link\"}))),\"Movement code\"),mdx(\"p\",null,\"Now we're finally ready to do the exciting part - let's make the ball move!\"),mdx(\"p\",null,\"First, let's set up the keys the player can press to move the ball. Go to \",mdx(\"inlineCode\",{parentName:\"p\"},\"Project > Project Settings > Input Map\"),\", and add the following keys:\"),mdx(\"p\",null,mdx(\"img\",a({parentName:\"p\"},{src:\"/illustrations/lets-roll/13-input-map.png\",alt:null}))),mdx(\"p\",null,\"Attach a new script to the the Ball (\",mdx(\"inlineCode\",{parentName:\"p\"},\"res://Player/Ball.gd\"),\"):\"),mdx(\"p\",null,mdx(\"img\",a({parentName:\"p\"},{src:\"/illustrations/lets-roll/13.1-attach-ball-script.png\",alt:null}))),mdx(\"p\",null,\"Add the following code:\"),mdx(\"pre\",null,mdx(\"code\",a({parentName:\"pre\"},{className:\"language-gdscript code-highlight\"}),mdx(\"span\",a({parentName:\"code\"},{className:\"code-line\"}),mdx(\"span\",a({parentName:\"span\"},{className:\"token keyword\"}),\"extends\"),\" \",mdx(\"span\",a({parentName:\"span\"},{className:\"token class-name\"}),\"RigidBody\"),`\n`),mdx(\"span\",a({parentName:\"code\"},{className:\"code-line\"}),`\n`),mdx(\"span\",a({parentName:\"code\"},{className:\"code-line\"}),\"\",mdx(\"span\",a({parentName:\"span\"},{className:\"token keyword\"}),\"var\"),\" rolling_force \",mdx(\"span\",a({parentName:\"span\"},{className:\"token operator\"}),\"=\"),\" \",mdx(\"span\",a({parentName:\"span\"},{className:\"token number\"}),\"40\"),`\n`),mdx(\"span\",a({parentName:\"code\"},{className:\"code-line\"}),`\n`),mdx(\"span\",a({parentName:\"code\"},{className:\"code-line\"}),\"\",mdx(\"span\",a({parentName:\"span\"},{className:\"token keyword\"}),\"func\"),\" \",mdx(\"span\",a({parentName:\"span\"},{className:\"token function\"}),\"_ready\"),mdx(\"span\",a({parentName:\"span\"},{className:\"token punctuation\"}),\"(\"),mdx(\"span\",a({parentName:\"span\"},{className:\"token punctuation\"}),\")\"),mdx(\"span\",a({parentName:\"span\"},{className:\"token punctuation\"}),\":\"),`\n`),mdx(\"span\",a({parentName:\"code\"},{className:\"code-line\"}),\"  \",mdx(\"span\",a({parentName:\"span\"},{className:\"token comment\"}),\"# Camera is parented to the Ball, but we don't want it to rotate\"),`\n`),mdx(\"span\",a({parentName:\"code\"},{className:\"code-line\"}),\"  \",mdx(\"span\",a({parentName:\"span\"},{className:\"token comment\"}),\"# along with the Ball. This line of code tells Godot to ignore the Ball's \"),`\n`),mdx(\"span\",a({parentName:\"code\"},{className:\"code-line\"}),\"  \",mdx(\"span\",a({parentName:\"span\"},{className:\"token comment\"}),\"# transformations, it will be as if the CameraRig is parented to Level01\"),`\n`),mdx(\"span\",a({parentName:\"code\"},{className:\"code-line\"}),\"  \",mdx(\"span\",a({parentName:\"span\"},{className:\"token variable\"}),\"$CameraRig\"),mdx(\"span\",a({parentName:\"span\"},{className:\"token punctuation\"}),\".\"),mdx(\"span\",a({parentName:\"span\"},{className:\"token function\"}),\"set_as_toplevel\"),mdx(\"span\",a({parentName:\"span\"},{className:\"token punctuation\"}),\"(\"),mdx(\"span\",a({parentName:\"span\"},{className:\"token boolean\"}),\"true\"),mdx(\"span\",a({parentName:\"span\"},{className:\"token punctuation\"}),\")\"),`\n`),mdx(\"span\",a({parentName:\"code\"},{className:\"code-line\"}),`\n`),mdx(\"span\",a({parentName:\"code\"},{className:\"code-line\"}),\"\",mdx(\"span\",a({parentName:\"span\"},{className:\"token keyword\"}),\"func\"),\" \",mdx(\"span\",a({parentName:\"span\"},{className:\"token function\"}),\"_physics_process\"),mdx(\"span\",a({parentName:\"span\"},{className:\"token punctuation\"}),\"(\"),\"delta\",mdx(\"span\",a({parentName:\"span\"},{className:\"token punctuation\"}),\")\"),mdx(\"span\",a({parentName:\"span\"},{className:\"token punctuation\"}),\":\"),`\n`),mdx(\"span\",a({parentName:\"code\"},{className:\"code-line\"}),\"  \",mdx(\"span\",a({parentName:\"span\"},{className:\"token comment\"}),\"# Move the ball in response to player pressing the buttons.\"),`\n`),mdx(\"span\",a({parentName:\"code\"},{className:\"code-line\"}),\"  \",mdx(\"span\",a({parentName:\"span\"},{className:\"token comment\"}),\"# When the button is pressed, we increase the angular velocity \"),`\n`),mdx(\"span\",a({parentName:\"code\"},{className:\"code-line\"}),\"  \",mdx(\"span\",a({parentName:\"span\"},{className:\"token comment\"}),\"# of the RigidBody in the corresponding dierction, making the ball spin.\"),`\n`),mdx(\"span\",a({parentName:\"code\"},{className:\"code-line\"}),\"  \",mdx(\"span\",a({parentName:\"span\"},{className:\"token comment\"}),\"# The rest is handled by the physics engine, when the ball spins - it rolls.\"),`\n`),mdx(\"span\",a({parentName:\"code\"},{className:\"code-line\"}),\"  \",mdx(\"span\",a({parentName:\"span\"},{className:\"token keyword\"}),\"if\"),\" Input\",mdx(\"span\",a({parentName:\"span\"},{className:\"token punctuation\"}),\".\"),mdx(\"span\",a({parentName:\"span\"},{className:\"token function\"}),\"is_action_pressed\"),mdx(\"span\",a({parentName:\"span\"},{className:\"token punctuation\"}),\"(\"),mdx(\"span\",a({parentName:\"span\"},{className:\"token string\"}),'\"forward\"'),mdx(\"span\",a({parentName:\"span\"},{className:\"token punctuation\"}),\")\"),mdx(\"span\",a({parentName:\"span\"},{className:\"token punctuation\"}),\":\"),`\n`),mdx(\"span\",a({parentName:\"code\"},{className:\"code-line\"}),\"    angular_velocity\",mdx(\"span\",a({parentName:\"span\"},{className:\"token punctuation\"}),\".\"),\"x \",mdx(\"span\",a({parentName:\"span\"},{className:\"token operator\"}),\"-=\"),\" rolling_force\",mdx(\"span\",a({parentName:\"span\"},{className:\"token operator\"}),\"*\"),`delta\n`),mdx(\"span\",a({parentName:\"code\"},{className:\"code-line\"}),\"  \",mdx(\"span\",a({parentName:\"span\"},{className:\"token keyword\"}),\"elif\"),\" Input\",mdx(\"span\",a({parentName:\"span\"},{className:\"token punctuation\"}),\".\"),mdx(\"span\",a({parentName:\"span\"},{className:\"token function\"}),\"is_action_pressed\"),mdx(\"span\",a({parentName:\"span\"},{className:\"token punctuation\"}),\"(\"),mdx(\"span\",a({parentName:\"span\"},{className:\"token string\"}),'\"back\"'),mdx(\"span\",a({parentName:\"span\"},{className:\"token punctuation\"}),\")\"),mdx(\"span\",a({parentName:\"span\"},{className:\"token punctuation\"}),\":\"),`\n`),mdx(\"span\",a({parentName:\"code\"},{className:\"code-line\"}),\"    angular_velocity\",mdx(\"span\",a({parentName:\"span\"},{className:\"token punctuation\"}),\".\"),\"x \",mdx(\"span\",a({parentName:\"span\"},{className:\"token operator\"}),\"+=\"),\" rolling_force\",mdx(\"span\",a({parentName:\"span\"},{className:\"token operator\"}),\"*\"),`delta\n`),mdx(\"span\",a({parentName:\"code\"},{className:\"code-line\"}),\"  \",mdx(\"span\",a({parentName:\"span\"},{className:\"token keyword\"}),\"if\"),\" Input\",mdx(\"span\",a({parentName:\"span\"},{className:\"token punctuation\"}),\".\"),mdx(\"span\",a({parentName:\"span\"},{className:\"token function\"}),\"is_action_pressed\"),mdx(\"span\",a({parentName:\"span\"},{className:\"token punctuation\"}),\"(\"),mdx(\"span\",a({parentName:\"span\"},{className:\"token string\"}),'\"left\"'),mdx(\"span\",a({parentName:\"span\"},{className:\"token punctuation\"}),\")\"),mdx(\"span\",a({parentName:\"span\"},{className:\"token punctuation\"}),\":\"),`\n`),mdx(\"span\",a({parentName:\"code\"},{className:\"code-line\"}),\"    angular_velocity\",mdx(\"span\",a({parentName:\"span\"},{className:\"token punctuation\"}),\".\"),\"z \",mdx(\"span\",a({parentName:\"span\"},{className:\"token operator\"}),\"+=\"),\" rolling_force\",mdx(\"span\",a({parentName:\"span\"},{className:\"token operator\"}),\"*\"),`delta\n`),mdx(\"span\",a({parentName:\"code\"},{className:\"code-line\"}),\"  \",mdx(\"span\",a({parentName:\"span\"},{className:\"token keyword\"}),\"elif\"),\" Input\",mdx(\"span\",a({parentName:\"span\"},{className:\"token punctuation\"}),\".\"),mdx(\"span\",a({parentName:\"span\"},{className:\"token function\"}),\"is_action_pressed\"),mdx(\"span\",a({parentName:\"span\"},{className:\"token punctuation\"}),\"(\"),mdx(\"span\",a({parentName:\"span\"},{className:\"token string\"}),'\"right\"'),mdx(\"span\",a({parentName:\"span\"},{className:\"token punctuation\"}),\")\"),mdx(\"span\",a({parentName:\"span\"},{className:\"token punctuation\"}),\":\"),`\n`),mdx(\"span\",a({parentName:\"code\"},{className:\"code-line\"}),\"    angular_velocity\",mdx(\"span\",a({parentName:\"span\"},{className:\"token punctuation\"}),\".\"),\"z \",mdx(\"span\",a({parentName:\"span\"},{className:\"token operator\"}),\"-=\"),\" rolling_force\",mdx(\"span\",a({parentName:\"span\"},{className:\"token operator\"}),\"*\"),`delta\n`))),mdx(\"p\",null,\"Now if you run the game, the ball is going to move in response to you pressing the buttons, but currently the camera stays in place (because we set it as top level, telling Godot to treat it as if it wasn't parented to the Ball). To move the camera along with the ball, add the following lines of code:\"),mdx(\"pre\",null,mdx(\"code\",a({parentName:\"pre\"},{className:\"language-gdscript code-highlight\"}),mdx(\"span\",a({parentName:\"code\"},{className:\"code-line\"}),mdx(\"span\",a({parentName:\"span\"},{className:\"token keyword\"}),\"extends\"),\" \",mdx(\"span\",a({parentName:\"span\"},{className:\"token class-name\"}),\"RigidBody\"),`\n`),mdx(\"span\",a({parentName:\"code\"},{className:\"code-line\"}),`\n`),mdx(\"span\",a({parentName:\"code\"},{className:\"code-line\"}),\"\",mdx(\"span\",a({parentName:\"span\"},{className:\"token keyword\"}),\"var\"),\" rolling_force \",mdx(\"span\",a({parentName:\"span\"},{className:\"token operator\"}),\"=\"),\" \",mdx(\"span\",a({parentName:\"span\"},{className:\"token number\"}),\"40\"),`\n`),mdx(\"span\",a({parentName:\"code\"},{className:\"code-line\"}),`\n`),mdx(\"span\",a({parentName:\"code\"},{className:\"code-line\"}),\"\",mdx(\"span\",a({parentName:\"span\"},{className:\"token keyword\"}),\"func\"),\" \",mdx(\"span\",a({parentName:\"span\"},{className:\"token function\"}),\"_ready\"),mdx(\"span\",a({parentName:\"span\"},{className:\"token punctuation\"}),\"(\"),mdx(\"span\",a({parentName:\"span\"},{className:\"token punctuation\"}),\")\"),mdx(\"span\",a({parentName:\"span\"},{className:\"token punctuation\"}),\":\"),`\n`),mdx(\"span\",a({parentName:\"code\"},{className:\"code-line\"}),\"    \",mdx(\"span\",a({parentName:\"span\"},{className:\"token variable\"}),\"$CameraRig\"),mdx(\"span\",a({parentName:\"span\"},{className:\"token punctuation\"}),\".\"),mdx(\"span\",a({parentName:\"span\"},{className:\"token function\"}),\"set_as_toplevel\"),mdx(\"span\",a({parentName:\"span\"},{className:\"token punctuation\"}),\"(\"),mdx(\"span\",a({parentName:\"span\"},{className:\"token boolean\"}),\"true\"),mdx(\"span\",a({parentName:\"span\"},{className:\"token punctuation\"}),\")\"),`\n`),mdx(\"span\",a({parentName:\"code\"},{className:\"code-line\"}),`  \n`),mdx(\"span\",a({parentName:\"code\"},{className:\"code-line\"}),\"\",mdx(\"span\",a({parentName:\"span\"},{className:\"token keyword\"}),\"func\"),\" \",mdx(\"span\",a({parentName:\"span\"},{className:\"token function\"}),\"_physics_process\"),mdx(\"span\",a({parentName:\"span\"},{className:\"token punctuation\"}),\"(\"),\"delta\",mdx(\"span\",a({parentName:\"span\"},{className:\"token punctuation\"}),\")\"),mdx(\"span\",a({parentName:\"span\"},{className:\"token punctuation\"}),\":\"),`\n`),mdx(\"span\",a({parentName:\"code\"},{className:\"code-line\"}),\"    \",mdx(\"span\",a({parentName:\"span\"},{className:\"token comment\"}),\"# Move the camera along with the ball\"),`\n`),mdx(\"span\",a({parentName:\"code\"},{className:\"code-line\"}),\"    \",mdx(\"span\",a({parentName:\"span\"},{className:\"token variable\"}),\"$CameraRig\"),mdx(\"span\",a({parentName:\"span\"},{className:\"token punctuation\"}),\".\"),\"global_transform\",mdx(\"span\",a({parentName:\"span\"},{className:\"token punctuation\"}),\".\"),\"origin \",mdx(\"span\",a({parentName:\"span\"},{className:\"token operator\"}),\"=\"),\" \",mdx(\"span\",a({parentName:\"span\"},{className:\"token function\"}),\"lerp\"),mdx(\"span\",a({parentName:\"span\"},{className:\"token punctuation\"}),\"(\"),`\n`),mdx(\"span\",a({parentName:\"code\"},{className:\"code-line\"}),\"        \",mdx(\"span\",a({parentName:\"span\"},{className:\"token variable\"}),\"$CameraRig\"),mdx(\"span\",a({parentName:\"span\"},{className:\"token punctuation\"}),\".\"),\"global_transform\",mdx(\"span\",a({parentName:\"span\"},{className:\"token punctuation\"}),\".\"),\"origin\",mdx(\"span\",a({parentName:\"span\"},{className:\"token punctuation\"}),\",\"),` \n`),mdx(\"span\",a({parentName:\"code\"},{className:\"code-line\"}),\"        global_transform\",mdx(\"span\",a({parentName:\"span\"},{className:\"token punctuation\"}),\".\"),\"origin\",mdx(\"span\",a({parentName:\"span\"},{className:\"token punctuation\"}),\",\"),\" \",mdx(\"span\",a({parentName:\"span\"},{className:\"token number\"}),\"0.1\"),`\n`),mdx(\"span\",a({parentName:\"code\"},{className:\"code-line\"}),\"    \",mdx(\"span\",a({parentName:\"span\"},{className:\"token punctuation\"}),\")\"),`\n`),mdx(\"span\",a({parentName:\"code\"},{className:\"code-line\"}),`\n`),mdx(\"span\",a({parentName:\"code\"},{className:\"code-line\"}),\"    \",mdx(\"span\",a({parentName:\"span\"},{className:\"token keyword\"}),\"if\"),\" Input\",mdx(\"span\",a({parentName:\"span\"},{className:\"token punctuation\"}),\".\"),mdx(\"span\",a({parentName:\"span\"},{className:\"token function\"}),\"is_action_pressed\"),mdx(\"span\",a({parentName:\"span\"},{className:\"token punctuation\"}),\"(\"),mdx(\"span\",a({parentName:\"span\"},{className:\"token string\"}),'\"forward\"'),mdx(\"span\",a({parentName:\"span\"},{className:\"token punctuation\"}),\")\"),mdx(\"span\",a({parentName:\"span\"},{className:\"token punctuation\"}),\":\"),`\n`),mdx(\"span\",a({parentName:\"code\"},{className:\"code-line\"}),\"        angular_velocity\",mdx(\"span\",a({parentName:\"span\"},{className:\"token punctuation\"}),\".\"),\"x \",mdx(\"span\",a({parentName:\"span\"},{className:\"token operator\"}),\"-=\"),\" rolling_force\",mdx(\"span\",a({parentName:\"span\"},{className:\"token operator\"}),\"*\"),`delta\n`),mdx(\"span\",a({parentName:\"code\"},{className:\"code-line\"}),\"    \",mdx(\"span\",a({parentName:\"span\"},{className:\"token keyword\"}),\"elif\"),\" Input\",mdx(\"span\",a({parentName:\"span\"},{className:\"token punctuation\"}),\".\"),mdx(\"span\",a({parentName:\"span\"},{className:\"token function\"}),\"is_action_pressed\"),mdx(\"span\",a({parentName:\"span\"},{className:\"token punctuation\"}),\"(\"),mdx(\"span\",a({parentName:\"span\"},{className:\"token string\"}),'\"back\"'),mdx(\"span\",a({parentName:\"span\"},{className:\"token punctuation\"}),\")\"),mdx(\"span\",a({parentName:\"span\"},{className:\"token punctuation\"}),\":\"),`\n`),mdx(\"span\",a({parentName:\"code\"},{className:\"code-line\"}),\"        angular_velocity\",mdx(\"span\",a({parentName:\"span\"},{className:\"token punctuation\"}),\".\"),\"x \",mdx(\"span\",a({parentName:\"span\"},{className:\"token operator\"}),\"+=\"),\" rolling_force\",mdx(\"span\",a({parentName:\"span\"},{className:\"token operator\"}),\"*\"),`delta\n`),mdx(\"span\",a({parentName:\"code\"},{className:\"code-line\"}),\"    \",mdx(\"span\",a({parentName:\"span\"},{className:\"token keyword\"}),\"if\"),\" Input\",mdx(\"span\",a({parentName:\"span\"},{className:\"token punctuation\"}),\".\"),mdx(\"span\",a({parentName:\"span\"},{className:\"token function\"}),\"is_action_pressed\"),mdx(\"span\",a({parentName:\"span\"},{className:\"token punctuation\"}),\"(\"),mdx(\"span\",a({parentName:\"span\"},{className:\"token string\"}),'\"left\"'),mdx(\"span\",a({parentName:\"span\"},{className:\"token punctuation\"}),\")\"),mdx(\"span\",a({parentName:\"span\"},{className:\"token punctuation\"}),\":\"),`\n`),mdx(\"span\",a({parentName:\"code\"},{className:\"code-line\"}),\"        angular_velocity\",mdx(\"span\",a({parentName:\"span\"},{className:\"token punctuation\"}),\".\"),\"z \",mdx(\"span\",a({parentName:\"span\"},{className:\"token operator\"}),\"+=\"),\" rolling_force\",mdx(\"span\",a({parentName:\"span\"},{className:\"token operator\"}),\"*\"),`delta\n`),mdx(\"span\",a({parentName:\"code\"},{className:\"code-line\"}),\"    \",mdx(\"span\",a({parentName:\"span\"},{className:\"token keyword\"}),\"elif\"),\" Input\",mdx(\"span\",a({parentName:\"span\"},{className:\"token punctuation\"}),\".\"),mdx(\"span\",a({parentName:\"span\"},{className:\"token function\"}),\"is_action_pressed\"),mdx(\"span\",a({parentName:\"span\"},{className:\"token punctuation\"}),\"(\"),mdx(\"span\",a({parentName:\"span\"},{className:\"token string\"}),'\"right\"'),mdx(\"span\",a({parentName:\"span\"},{className:\"token punctuation\"}),\")\"),mdx(\"span\",a({parentName:\"span\"},{className:\"token punctuation\"}),\":\"),`\n`),mdx(\"span\",a({parentName:\"code\"},{className:\"code-line\"}),\"        angular_velocity\",mdx(\"span\",a({parentName:\"span\"},{className:\"token punctuation\"}),\".\"),\"z \",mdx(\"span\",a({parentName:\"span\"},{className:\"token operator\"}),\"-=\"),\" rolling_force\",mdx(\"span\",a({parentName:\"span\"},{className:\"token operator\"}),\"*\"),`delta\n`),mdx(\"span\",a({parentName:\"code\"},{className:\"code-line\"}),`\n`))),mdx(\"p\",null,\"We're setting CameraRig's global position to be equal to Ball's global translation (\",mdx(\"inlineCode\",{parentName:\"p\"},\"global_transform.origin\"),\"). \",mdx(\"a\",a({parentName:\"p\"},{href:\"https://docs.godotengine.org/en/3.2/classes/class_@gdscript.html#class-gdscript-method-lerp\"}),\"lerp\"),\" stands for linear interpolation, it will make it so that the camera position follows the ball smoothly instead of instantaneously, so if the ball suddenly jumps up, it will take the camera a few frames to catch up with it.\"),mdx(\"h3\",a({},{id:\"jump-functionality\"}),mdx(\"a\",a({parentName:\"h3\"},{className:\"header-link\",href:\"#jump-functionality\"}),mdx(\"span\",a({parentName:\"a\"},{className:\"icon icon-link\"}))),\"Jump Functionality\"),mdx(\"p\",null,\"Now let's add the jumping functionality. In the Ball scene, add a \",mdx(\"inlineCode\",{parentName:\"p\"},\"RayCast\"),' node, rename it to \"FloorCheck\", and set its properties like so:'),mdx(\"p\",null,mdx(\"img\",a({parentName:\"p\"},{src:\"/illustrations/lets-roll/14-raycast-settings.png\",alt:null}))),mdx(\"p\",null,\"Imagine the raycast as a small arrow pointing downwards from the center of the Ball, it is just a bit longer than the ball's radius. We can check whether this arrow intersects with the floor, if it does - we know that the Ball is on the ground, and we are able to jump. If it doesn't, we know that the Ball is currently in the air, and we don't want the player to be able to jump when its already in the air.\"),mdx(\"p\",null,\"Here's how the final Ball movement code looks like:\"),mdx(\"pre\",null,mdx(\"code\",a({parentName:\"pre\"},{className:\"language-gdscript code-highlight\"}),mdx(\"span\",a({parentName:\"code\"},{className:\"code-line\"}),mdx(\"span\",a({parentName:\"span\"},{className:\"token keyword\"}),\"extends\"),\" \",mdx(\"span\",a({parentName:\"span\"},{className:\"token class-name\"}),\"RigidBody\"),`\n`),mdx(\"span\",a({parentName:\"code\"},{className:\"code-line\"}),`\n`),mdx(\"span\",a({parentName:\"code\"},{className:\"code-line\"}),\"\",mdx(\"span\",a({parentName:\"span\"},{className:\"token keyword\"}),\"var\"),\" rolling_force \",mdx(\"span\",a({parentName:\"span\"},{className:\"token operator\"}),\"=\"),\" \",mdx(\"span\",a({parentName:\"span\"},{className:\"token number\"}),\"40\"),`\n`),mdx(\"span\",a({parentName:\"code\"},{className:\"code-line\"}),`\n`),mdx(\"span\",a({parentName:\"code\"},{className:\"code-line\"}),\"\",mdx(\"span\",a({parentName:\"span\"},{className:\"token keyword\"}),\"func\"),\" \",mdx(\"span\",a({parentName:\"span\"},{className:\"token function\"}),\"_ready\"),mdx(\"span\",a({parentName:\"span\"},{className:\"token punctuation\"}),\"(\"),mdx(\"span\",a({parentName:\"span\"},{className:\"token punctuation\"}),\")\"),mdx(\"span\",a({parentName:\"span\"},{className:\"token punctuation\"}),\":\"),`\n`),mdx(\"span\",a({parentName:\"code\"},{className:\"code-line\"}),\"    \",mdx(\"span\",a({parentName:\"span\"},{className:\"token variable\"}),\"$CameraRig\"),mdx(\"span\",a({parentName:\"span\"},{className:\"token punctuation\"}),\".\"),mdx(\"span\",a({parentName:\"span\"},{className:\"token function\"}),\"set_as_toplevel\"),mdx(\"span\",a({parentName:\"span\"},{className:\"token punctuation\"}),\"(\"),mdx(\"span\",a({parentName:\"span\"},{className:\"token boolean\"}),\"true\"),mdx(\"span\",a({parentName:\"span\"},{className:\"token punctuation\"}),\")\"),`\n`),mdx(\"span\",a({parentName:\"code\"},{className:\"code-line\"}),\"    \",mdx(\"span\",a({parentName:\"span\"},{className:\"token comment\"}),\"# Make sure FloorCheck raycast doesn't inherit Balls transforms,\"),`\n`),mdx(\"span\",a({parentName:\"code\"},{className:\"code-line\"}),\"    \",mdx(\"span\",a({parentName:\"span\"},{className:\"token comment\"}),\"# so that it doesn't rotate as the ball rolls\"),`\n`),mdx(\"span\",a({parentName:\"code\"},{className:\"code-line\"}),\"    \",mdx(\"span\",a({parentName:\"span\"},{className:\"token variable\"}),\"$FloorCheck\"),mdx(\"span\",a({parentName:\"span\"},{className:\"token punctuation\"}),\".\"),mdx(\"span\",a({parentName:\"span\"},{className:\"token function\"}),\"set_as_toplevel\"),mdx(\"span\",a({parentName:\"span\"},{className:\"token punctuation\"}),\"(\"),mdx(\"span\",a({parentName:\"span\"},{className:\"token boolean\"}),\"true\"),mdx(\"span\",a({parentName:\"span\"},{className:\"token punctuation\"}),\")\"),`\n`),mdx(\"span\",a({parentName:\"code\"},{className:\"code-line\"}),`\n`),mdx(\"span\",a({parentName:\"code\"},{className:\"code-line\"}),\"\",mdx(\"span\",a({parentName:\"span\"},{className:\"token keyword\"}),\"func\"),\" \",mdx(\"span\",a({parentName:\"span\"},{className:\"token function\"}),\"_physics_process\"),mdx(\"span\",a({parentName:\"span\"},{className:\"token punctuation\"}),\"(\"),\"delta\",mdx(\"span\",a({parentName:\"span\"},{className:\"token punctuation\"}),\")\"),mdx(\"span\",a({parentName:\"span\"},{className:\"token punctuation\"}),\":\"),`\n`),mdx(\"span\",a({parentName:\"code\"},{className:\"code-line\"}),\"    \",mdx(\"span\",a({parentName:\"span\"},{className:\"token variable\"}),\"$CameraRig\"),mdx(\"span\",a({parentName:\"span\"},{className:\"token punctuation\"}),\".\"),\"global_transform\",mdx(\"span\",a({parentName:\"span\"},{className:\"token punctuation\"}),\".\"),\"origin \",mdx(\"span\",a({parentName:\"span\"},{className:\"token operator\"}),\"=\"),\" \",mdx(\"span\",a({parentName:\"span\"},{className:\"token function\"}),\"lerp\"),mdx(\"span\",a({parentName:\"span\"},{className:\"token punctuation\"}),\"(\"),`\n`),mdx(\"span\",a({parentName:\"code\"},{className:\"code-line\"}),\"        \",mdx(\"span\",a({parentName:\"span\"},{className:\"token variable\"}),\"$CameraRig\"),mdx(\"span\",a({parentName:\"span\"},{className:\"token punctuation\"}),\".\"),\"global_transform\",mdx(\"span\",a({parentName:\"span\"},{className:\"token punctuation\"}),\".\"),\"origin\",mdx(\"span\",a({parentName:\"span\"},{className:\"token punctuation\"}),\",\"),` \n`),mdx(\"span\",a({parentName:\"code\"},{className:\"code-line\"}),\"        global_transform\",mdx(\"span\",a({parentName:\"span\"},{className:\"token punctuation\"}),\".\"),\"origin\",mdx(\"span\",a({parentName:\"span\"},{className:\"token punctuation\"}),\",\"),\" \",mdx(\"span\",a({parentName:\"span\"},{className:\"token number\"}),\"0.1\"),`\n`),mdx(\"span\",a({parentName:\"code\"},{className:\"code-line\"}),\"    \",mdx(\"span\",a({parentName:\"span\"},{className:\"token punctuation\"}),\")\"),`\n`),mdx(\"span\",a({parentName:\"code\"},{className:\"code-line\"}),\"    \",mdx(\"span\",a({parentName:\"span\"},{className:\"token comment\"}),\"# As the ball moves, move the raycast along with it\"),`\n`),mdx(\"span\",a({parentName:\"code\"},{className:\"code-line\"}),\"    \",mdx(\"span\",a({parentName:\"span\"},{className:\"token variable\"}),\"$FloorCheck\"),mdx(\"span\",a({parentName:\"span\"},{className:\"token punctuation\"}),\".\"),\"global_transform\",mdx(\"span\",a({parentName:\"span\"},{className:\"token punctuation\"}),\".\"),\"origin \",mdx(\"span\",a({parentName:\"span\"},{className:\"token operator\"}),\"=\"),\" global_transform\",mdx(\"span\",a({parentName:\"span\"},{className:\"token punctuation\"}),\".\"),`origin\n`),mdx(\"span\",a({parentName:\"code\"},{className:\"code-line\"}),`\n`),mdx(\"span\",a({parentName:\"code\"},{className:\"code-line\"}),\"    \",mdx(\"span\",a({parentName:\"span\"},{className:\"token keyword\"}),\"if\"),\" Input\",mdx(\"span\",a({parentName:\"span\"},{className:\"token punctuation\"}),\".\"),mdx(\"span\",a({parentName:\"span\"},{className:\"token function\"}),\"is_action_pressed\"),mdx(\"span\",a({parentName:\"span\"},{className:\"token punctuation\"}),\"(\"),mdx(\"span\",a({parentName:\"span\"},{className:\"token string\"}),'\"forward\"'),mdx(\"span\",a({parentName:\"span\"},{className:\"token punctuation\"}),\")\"),mdx(\"span\",a({parentName:\"span\"},{className:\"token punctuation\"}),\":\"),`\n`),mdx(\"span\",a({parentName:\"code\"},{className:\"code-line\"}),\"        angular_velocity\",mdx(\"span\",a({parentName:\"span\"},{className:\"token punctuation\"}),\".\"),\"x \",mdx(\"span\",a({parentName:\"span\"},{className:\"token operator\"}),\"-=\"),\" rolling_force\",mdx(\"span\",a({parentName:\"span\"},{className:\"token operator\"}),\"*\"),`delta\n`),mdx(\"span\",a({parentName:\"code\"},{className:\"code-line\"}),\"    \",mdx(\"span\",a({parentName:\"span\"},{className:\"token keyword\"}),\"elif\"),\" Input\",mdx(\"span\",a({parentName:\"span\"},{className:\"token punctuation\"}),\".\"),mdx(\"span\",a({parentName:\"span\"},{className:\"token function\"}),\"is_action_pressed\"),mdx(\"span\",a({parentName:\"span\"},{className:\"token punctuation\"}),\"(\"),mdx(\"span\",a({parentName:\"span\"},{className:\"token string\"}),'\"back\"'),mdx(\"span\",a({parentName:\"span\"},{className:\"token punctuation\"}),\")\"),mdx(\"span\",a({parentName:\"span\"},{className:\"token punctuation\"}),\":\"),`\n`),mdx(\"span\",a({parentName:\"code\"},{className:\"code-line\"}),\"        angular_velocity\",mdx(\"span\",a({parentName:\"span\"},{className:\"token punctuation\"}),\".\"),\"x \",mdx(\"span\",a({parentName:\"span\"},{className:\"token operator\"}),\"+=\"),\" rolling_force\",mdx(\"span\",a({parentName:\"span\"},{className:\"token operator\"}),\"*\"),`delta\n`),mdx(\"span\",a({parentName:\"code\"},{className:\"code-line\"}),\"    \",mdx(\"span\",a({parentName:\"span\"},{className:\"token keyword\"}),\"if\"),\" Input\",mdx(\"span\",a({parentName:\"span\"},{className:\"token punctuation\"}),\".\"),mdx(\"span\",a({parentName:\"span\"},{className:\"token function\"}),\"is_action_pressed\"),mdx(\"span\",a({parentName:\"span\"},{className:\"token punctuation\"}),\"(\"),mdx(\"span\",a({parentName:\"span\"},{className:\"token string\"}),'\"left\"'),mdx(\"span\",a({parentName:\"span\"},{className:\"token punctuation\"}),\")\"),mdx(\"span\",a({parentName:\"span\"},{className:\"token punctuation\"}),\":\"),`\n`),mdx(\"span\",a({parentName:\"code\"},{className:\"code-line\"}),\"        angular_velocity\",mdx(\"span\",a({parentName:\"span\"},{className:\"token punctuation\"}),\".\"),\"z \",mdx(\"span\",a({parentName:\"span\"},{className:\"token operator\"}),\"+=\"),\" rolling_force\",mdx(\"span\",a({parentName:\"span\"},{className:\"token operator\"}),\"*\"),`delta\n`),mdx(\"span\",a({parentName:\"code\"},{className:\"code-line\"}),\"    \",mdx(\"span\",a({parentName:\"span\"},{className:\"token keyword\"}),\"elif\"),\" Input\",mdx(\"span\",a({parentName:\"span\"},{className:\"token punctuation\"}),\".\"),mdx(\"span\",a({parentName:\"span\"},{className:\"token function\"}),\"is_action_pressed\"),mdx(\"span\",a({parentName:\"span\"},{className:\"token punctuation\"}),\"(\"),mdx(\"span\",a({parentName:\"span\"},{className:\"token string\"}),'\"right\"'),mdx(\"span\",a({parentName:\"span\"},{className:\"token punctuation\"}),\")\"),mdx(\"span\",a({parentName:\"span\"},{className:\"token punctuation\"}),\":\"),`\n`),mdx(\"span\",a({parentName:\"code\"},{className:\"code-line\"}),\"        angular_velocity\",mdx(\"span\",a({parentName:\"span\"},{className:\"token punctuation\"}),\".\"),\"z \",mdx(\"span\",a({parentName:\"span\"},{className:\"token operator\"}),\"-=\"),\" rolling_force\",mdx(\"span\",a({parentName:\"span\"},{className:\"token operator\"}),\"*\"),`delta\n`),mdx(\"span\",a({parentName:\"code\"},{className:\"code-line\"}),`\n`),mdx(\"span\",a({parentName:\"code\"},{className:\"code-line\"}),\"    \",mdx(\"span\",a({parentName:\"span\"},{className:\"token comment\"}),\"# When the ball is on the floor and the user presses jump button,\"),`\n`),mdx(\"span\",a({parentName:\"code\"},{className:\"code-line\"}),\"    \",mdx(\"span\",a({parentName:\"span\"},{className:\"token comment\"}),\"# add impulse moving the ball up.\"),`\n`),mdx(\"span\",a({parentName:\"code\"},{className:\"code-line\"}),\"    \",mdx(\"span\",a({parentName:\"span\"},{className:\"token keyword\"}),\"if\"),\" Input\",mdx(\"span\",a({parentName:\"span\"},{className:\"token punctuation\"}),\".\"),mdx(\"span\",a({parentName:\"span\"},{className:\"token function\"}),\"is_action_just_pressed\"),mdx(\"span\",a({parentName:\"span\"},{className:\"token punctuation\"}),\"(\"),mdx(\"span\",a({parentName:\"span\"},{className:\"token string\"}),'\"jump\"'),mdx(\"span\",a({parentName:\"span\"},{className:\"token punctuation\"}),\")\"),\" \",mdx(\"span\",a({parentName:\"span\"},{className:\"token keyword\"}),\"and\"),\" \",mdx(\"span\",a({parentName:\"span\"},{className:\"token variable\"}),\"$FloorCheck\"),mdx(\"span\",a({parentName:\"span\"},{className:\"token punctuation\"}),\".\"),mdx(\"span\",a({parentName:\"span\"},{className:\"token function\"}),\"is_colliding\"),mdx(\"span\",a({parentName:\"span\"},{className:\"token punctuation\"}),\"(\"),mdx(\"span\",a({parentName:\"span\"},{className:\"token punctuation\"}),\")\"),mdx(\"span\",a({parentName:\"span\"},{className:\"token punctuation\"}),\":\"),`\n`),mdx(\"span\",a({parentName:\"code\"},{className:\"code-line\"}),\"        \",mdx(\"span\",a({parentName:\"span\"},{className:\"token function\"}),\"apply_impulse\"),mdx(\"span\",a({parentName:\"span\"},{className:\"token punctuation\"}),\"(\"),mdx(\"span\",a({parentName:\"span\"},{className:\"token function\"}),\"Vector3\"),mdx(\"span\",a({parentName:\"span\"},{className:\"token punctuation\"}),\"(\"),mdx(\"span\",a({parentName:\"span\"},{className:\"token punctuation\"}),\")\"),mdx(\"span\",a({parentName:\"span\"},{className:\"token punctuation\"}),\",\"),\" Vector3\",mdx(\"span\",a({parentName:\"span\"},{className:\"token punctuation\"}),\".\"),mdx(\"span\",a({parentName:\"span\"},{className:\"token constant\"}),\"UP\"),mdx(\"span\",a({parentName:\"span\"},{className:\"token operator\"}),\"*\"),mdx(\"span\",a({parentName:\"span\"},{className:\"token number\"}),\"1000\"),mdx(\"span\",a({parentName:\"span\"},{className:\"token punctuation\"}),\")\"),`\n`),mdx(\"span\",a({parentName:\"code\"},{className:\"code-line\"}),`\n`))),mdx(\"p\",null,\"Raycast is parented under the ball, and as the ball is rolling, raycast arrow would rotate along with it. We don't want that, we want it to be constantly pointing downwards, so we use the same trick we used with the camera - we use \",mdx(\"inlineCode\",{parentName:\"p\"},\"set_as_toplevel\"),\" to tell Godot to ignore the fact that raycast is parented to the ball, and then in the \",mdx(\"inlineCode\",{parentName:\"p\"},\"_physics_process()\"),\" we set raycast's position to always be equal to the ball's global translation, so that it moves along with the ball (but doesn't rotate with it).\"),mdx(\"p\",null,mdx(\"inlineCode\",{parentName:\"p\"},\"$FloorCheck.is_colliding()\"),\" tells us whether the raycast intersects with he floor. If the ball is on the floor and the player has just pressed the jump button, we propel the Ball upwards using \",mdx(\"inlineCode\",{parentName:\"p\"},\"apply_impulse()\"),\".\"),mdx(\"h3\",a({},{id:\"tweaking-ball-physics-settings\"}),mdx(\"a\",a({parentName:\"h3\"},{className:\"header-link\",href:\"#tweaking-ball-physics-settings\"}),mdx(\"span\",a({parentName:\"a\"},{className:\"icon icon-link\"}))),\"Tweaking Ball Physics settings\"),mdx(\"p\",null,\"If you try playing the game now, you'll notice that the ball feels too light and too slippery. We want to modify its physics properties so that the gameplay feels more fun and controllable. Click on the Ball node, assign it a new Physics Material, and modify the settings as follows:\"),mdx(\"p\",null,mdx(\"img\",a({parentName:\"p\"},{src:\"/illustrations/lets-roll/15-ball-physics-settings.png\",alt:null}))),mdx(\"p\",null,\"We make it heavier and increase the friction with the floor to make the Ball easier to control. We add some bounciness to make the ball bounce off the floor and walls, making it more fun and challenging to play.\"),mdx(\"p\",null,\"Also set \",mdx(\"inlineCode\",{parentName:\"p\"},\"Angular > Damp\"),\" to \",mdx(\"inlineCode\",{parentName:\"p\"},\"1\"),\", so that ball gradually comes to a halt when we don't press any buttons.\"),mdx(\"p\",null,\"Finally, you want to go to \",mdx(\"inlineCode\",{parentName:\"p\"},\"Project > Project Settings > Physics > 3D\"),\" and switch \",mdx(\"inlineCode\",{parentName:\"p\"},\"Physics Engine\"),` to \"GodotPhysics\". There are two different physics engines in Godot, and I chose this one because the other one doesn't work when you export the game to be playable in the browser.`),mdx(\"h1\",a({},{id:\"lighting-and-render-settings\"}),mdx(\"a\",a({parentName:\"h1\"},{className:\"header-link\",href:\"#lighting-and-render-settings\"}),mdx(\"span\",a({parentName:\"a\"},{className:\"icon icon-link\"}))),\"Lighting and Render Settings\"),mdx(\"p\",null,\"Now it's time to make our game look pretty. First go to \",mdx(\"inlineCode\",{parentName:\"p\"},\"Project > Project Settings\"),\" and set the following settings:\"),mdx(\"ul\",null,mdx(\"li\",{parentName:\"ul\"},mdx(\"inlineCode\",{parentName:\"li\"},\"Window > Width and Height\"),\": \",mdx(\"strong\",{parentName:\"li\"},\"1024x576\"),mdx(\"br\",{parentName:\"li\"}),\"(sets the default game resolution).\"),mdx(\"li\",{parentName:\"ul\"},mdx(\"inlineCode\",{parentName:\"li\"},\"Window > Stretch > Mode\"),\": \",mdx(\"strong\",{parentName:\"li\"},\"2D\"),\", \",mdx(\"inlineCode\",{parentName:\"li\"},\"Aspect\"),\": \",mdx(\"strong\",{parentName:\"li\"},\"keep\"),\".\",mdx(\"br\",{parentName:\"li\"}),\"(makes it possible to resize the game window, and scale the picture according to its size).\"),mdx(\"li\",{parentName:\"ul\"},mdx(\"inlineCode\",{parentName:\"li\"},\"Rendering > Quality > Msaa\"),\": \",mdx(\"strong\",{parentName:\"li\"},\"4x\"),\".\",mdx(\"br\",{parentName:\"li\"}),\"(enables anti-aliasing, which removes the jagged lines at the edges of the objects).\"),mdx(\"li\",{parentName:\"ul\"},mdx(\"inlineCode\",{parentName:\"li\"},\"Rendering > Quality > Directional Shadow > Size\"),\": \",mdx(\"strong\",{parentName:\"li\"},\"8192\"),mdx(\"br\",{parentName:\"li\"}),\"(improves the shadow quality).\")),mdx(\"p\",null,\"Add a new \",mdx(\"inlineCode\",{parentName:\"p\"},\"WorldEnvironment\"),\" node to the Level01, create a new environment and set the settings as follows:\"),mdx(\"p\",null,mdx(\"img\",a({parentName:\"p\"},{src:\"/illustrations/lets-roll/16-world-environment-settings.png\",alt:null}))),mdx(\"p\",null,\"WorldEnvironment allows us to change the ambient lighting (which we set to the color of the sky), and add post-processing effects like fog and color correction.\"),mdx(\"ul\",null,mdx(\"li\",{parentName:\"ul\"},\"Custom Color - \",mdx(\"inlineCode\",{parentName:\"li\"},\"#2b79ad\")),mdx(\"li\",{parentName:\"ul\"},\"Ambient light - \",mdx(\"inlineCode\",{parentName:\"li\"},\"#1eacf1\")),mdx(\"li\",{parentName:\"ul\"},\"Fog enabled, color - \",mdx(\"inlineCode\",{parentName:\"li\"},\"#6792bd\")),mdx(\"li\",{parentName:\"ul\"},\"Tonemap - ACES\")),mdx(\"p\",null,\"Add a \",mdx(\"inlineCode\",{parentName:\"p\"},\"DirectionalLight\"),\", it will represent the main light in the scene (the sun). Set:\"),mdx(\"ul\",null,mdx(\"li\",{parentName:\"ul\"},\"Color - \",mdx(\"inlineCode\",{parentName:\"li\"},\"#f8e6cd\")),mdx(\"li\",{parentName:\"ul\"},\"Energy - 2\"),mdx(\"li\",{parentName:\"ul\"},\"Shadow - Enabled.\"),mdx(\"li\",{parentName:\"ul\"},\"Rotation - \",mdx(\"inlineCode\",{parentName:\"li\"},\"-60, 60, 0\"))),mdx(\"p\",null,\"The final look of the game:\"),mdx(\"p\",null,mdx(\"img\",a({parentName:\"p\"},{src:\"/illustrations/lets-roll/17-final-look.png\",alt:null}))),mdx(\"h2\",a({},{id:\"deathzone\"}),mdx(\"a\",a({parentName:\"h2\"},{className:\"header-link\",href:\"#deathzone\"}),mdx(\"span\",a({parentName:\"a\"},{className:\"icon icon-link\"}))),\"DeathZone\"),mdx(\"p\",null,\"Next, we want to restart the game when the ball rolls off the level. Create a new \",mdx(\"inlineCode\",{parentName:\"p\"},\"Area\"),' node, name it \"DeathZone\" and save it into ',mdx(\"inlineCode\",{parentName:\"p\"},\"res://Environment/DeathZone.tscn\"),\". Add a collision shape to it, create the BoxShape, make it pretty large (set its extents to \",mdx(\"inlineCode\",{parentName:\"p\"},\"150, 1, 150\"),\"), and set it's translation y to \",mdx(\"inlineCode\",{parentName:\"p\"},\"-10\"),\" to move it below the ground:\"),mdx(\"p\",null,mdx(\"img\",a({parentName:\"p\"},{src:\"/illustrations/lets-roll/18-death-zone.png\",alt:null}))),mdx(\"p\",null,\"Link this scene into the level (Level01). When the ball falls off the level, it will cross the DeathZone, and we'll know that we need to restart the game.\"),mdx(\"p\",null,`First, let's attach a new script to the Level01 node, and call this script \"Level.gd\":`),mdx(\"p\",null,mdx(\"img\",a({parentName:\"p\"},{src:\"/illustrations/lets-roll/18.1-attach-level-script.png\",alt:null}))),mdx(\"p\",null,`Note that we're naming this script \"Level.gd\" not \"Level01.gd\" - when we have more levels, this script will be attached to them as well.`),mdx(\"p\",null,\"Now, select the DeathZone node, open the Node panel, and connect the \",mdx(\"inlineCode\",{parentName:\"p\"},\"body_entered\"),` signal of DeathZone to the Level script:\n`,mdx(\"img\",a({parentName:\"p\"},{src:\"/illustrations/lets-roll/18.2-death-zone-connect-signal.png\",alt:null}))),mdx(\"p\",null,\"Godot will automatically create \",mdx(\"inlineCode\",{parentName:\"p\"},\"_on_DeathZone_body_entered()\"),\" function for you, this function will trigger every time our Ball falls down and enters the DeathZone. Now we just need to tell Godot to reload the level as soon as that happens:\"),mdx(\"pre\",null,mdx(\"code\",a({parentName:\"pre\"},{className:\"language-gdscript code-highlight\"}),mdx(\"span\",a({parentName:\"code\"},{className:\"code-line\"}),mdx(\"span\",a({parentName:\"span\"},{className:\"token keyword\"}),\"func\"),\" \",mdx(\"span\",a({parentName:\"span\"},{className:\"token function\"}),\"_on_DeathZone_body_entered\"),mdx(\"span\",a({parentName:\"span\"},{className:\"token punctuation\"}),\"(\"),\"body\",mdx(\"span\",a({parentName:\"span\"},{className:\"token punctuation\"}),\")\"),mdx(\"span\",a({parentName:\"span\"},{className:\"token punctuation\"}),\":\"),`\n`),mdx(\"span\",a({parentName:\"code\"},{className:\"code-line\"}),\"    \",mdx(\"span\",a({parentName:\"span\"},{className:\"token keyword\"}),\"if\"),\" body\",mdx(\"span\",a({parentName:\"span\"},{className:\"token punctuation\"}),\".\"),\"name \",mdx(\"span\",a({parentName:\"span\"},{className:\"token operator\"}),\"==\"),\" \",mdx(\"span\",a({parentName:\"span\"},{className:\"token string\"}),'\"Ball\"'),mdx(\"span\",a({parentName:\"span\"},{className:\"token punctuation\"}),\":\"),`\n`),mdx(\"span\",a({parentName:\"code\"},{className:\"code-line\"}),\"        \",mdx(\"span\",a({parentName:\"span\"},{className:\"token function\"}),\"get_tree\"),mdx(\"span\",a({parentName:\"span\"},{className:\"token punctuation\"}),\"(\"),mdx(\"span\",a({parentName:\"span\"},{className:\"token punctuation\"}),\")\"),mdx(\"span\",a({parentName:\"span\"},{className:\"token punctuation\"}),\".\"),mdx(\"span\",a({parentName:\"span\"},{className:\"token function\"}),\"reload_current_scene\"),mdx(\"span\",a({parentName:\"span\"},{className:\"token punctuation\"}),\"(\"),mdx(\"span\",a({parentName:\"span\"},{className:\"token punctuation\"}),\")\"),`\n`))),mdx(\"h2\",a({},{id:\"victoryzone-and-levels\"}),mdx(\"a\",a({parentName:\"h2\"},{className:\"header-link\",href:\"#victoryzone-and-levels\"}),mdx(\"span\",a({parentName:\"a\"},{className:\"icon icon-link\"}))),\"VictoryZone and Levels.\"),mdx(\"p\",null,\"Finally, one last thing we want to do is to add levels. As soon as the ball reaches its target, we want to move the player to the next level.\"),mdx(\"p\",null,\"Just like with the DeathZone - create a new \",mdx(\"inlineCode\",{parentName:\"p\"},\"Area\"),` scene, name it \"VictoryZone\", add a Box collision shape, link it into the Level01, and place it where the Ball's target is:`),mdx(\"p\",null,mdx(\"img\",a({parentName:\"p\"},{src:\"/illustrations/lets-roll/19-victory-zone.png\",alt:null}))),mdx(\"p\",null,\"And just like with DeathZone, we want to connect the \",mdx(\"inlineCode\",{parentName:\"p\"},\"body_entered\"),\" signal from VictoryZone to Level script. As soon as the Ball enters the VictoryZone, we will run a function that moves us to the next level.\"),mdx(\"p\",null,\"Add the following code to the Level.gd script:\"),mdx(\"pre\",null,mdx(\"code\",a({parentName:\"pre\"},{className:\"language-gdscript code-highlight\"}),mdx(\"span\",a({parentName:\"code\"},{className:\"code-line\"}),mdx(\"span\",a({parentName:\"span\"},{className:\"token keyword\"}),\"var\"),\" levels \",mdx(\"span\",a({parentName:\"span\"},{className:\"token operator\"}),\"=\"),\" \",mdx(\"span\",a({parentName:\"span\"},{className:\"token punctuation\"}),\"[\"),`\n`),mdx(\"span\",a({parentName:\"code\"},{className:\"code-line\"}),\"    \",mdx(\"span\",a({parentName:\"span\"},{className:\"token string\"}),'\"res://Environment/Level01.tscn\"'),mdx(\"span\",a({parentName:\"span\"},{className:\"token punctuation\"}),\",\"),`\n`),mdx(\"span\",a({parentName:\"code\"},{className:\"code-line\"}),\"    \",mdx(\"span\",a({parentName:\"span\"},{className:\"token string\"}),'\"res://Environment/Level02.tscn\"'),`\n`),mdx(\"span\",a({parentName:\"code\"},{className:\"code-line\"}),\"\",mdx(\"span\",a({parentName:\"span\"},{className:\"token punctuation\"}),\"]\"),`\n`),mdx(\"span\",a({parentName:\"code\"},{className:\"code-line\"}),\"\",mdx(\"span\",a({parentName:\"span\"},{className:\"token keyword\"}),\"export\"),\" \",mdx(\"span\",a({parentName:\"span\"},{className:\"token keyword\"}),\"var\"),\" current_level \",mdx(\"span\",a({parentName:\"span\"},{className:\"token operator\"}),\"=\"),\" \",mdx(\"span\",a({parentName:\"span\"},{className:\"token number\"}),\"0\"),`\n`),mdx(\"span\",a({parentName:\"code\"},{className:\"code-line\"}),`\n`),mdx(\"span\",a({parentName:\"code\"},{className:\"code-line\"}),\"\",mdx(\"span\",a({parentName:\"span\"},{className:\"token keyword\"}),\"func\"),\" \",mdx(\"span\",a({parentName:\"span\"},{className:\"token function\"}),\"_on_VictoryZone_body_entered\"),mdx(\"span\",a({parentName:\"span\"},{className:\"token punctuation\"}),\"(\"),\"body\",mdx(\"span\",a({parentName:\"span\"},{className:\"token punctuation\"}),\")\"),mdx(\"span\",a({parentName:\"span\"},{className:\"token punctuation\"}),\":\"),`\n`),mdx(\"span\",a({parentName:\"code\"},{className:\"code-line\"}),\"    \",mdx(\"span\",a({parentName:\"span\"},{className:\"token keyword\"}),\"if\"),\" body\",mdx(\"span\",a({parentName:\"span\"},{className:\"token punctuation\"}),\".\"),\"name \",mdx(\"span\",a({parentName:\"span\"},{className:\"token operator\"}),\"==\"),\" \",mdx(\"span\",a({parentName:\"span\"},{className:\"token string\"}),'\"Ball\"'),mdx(\"span\",a({parentName:\"span\"},{className:\"token punctuation\"}),\":\"),`\n`),mdx(\"span\",a({parentName:\"code\"},{className:\"code-line\"}),\"        current_level \",mdx(\"span\",a({parentName:\"span\"},{className:\"token operator\"}),\"+=\"),\" \",mdx(\"span\",a({parentName:\"span\"},{className:\"token number\"}),\"1\"),`\n`),mdx(\"span\",a({parentName:\"code\"},{className:\"code-line\"}),\"        \",mdx(\"span\",a({parentName:\"span\"},{className:\"token keyword\"}),\"if\"),\" current_level \",mdx(\"span\",a({parentName:\"span\"},{className:\"token operator\"}),\"<\"),\" levels\",mdx(\"span\",a({parentName:\"span\"},{className:\"token punctuation\"}),\".\"),mdx(\"span\",a({parentName:\"span\"},{className:\"token function\"}),\"size\"),mdx(\"span\",a({parentName:\"span\"},{className:\"token punctuation\"}),\"(\"),mdx(\"span\",a({parentName:\"span\"},{className:\"token punctuation\"}),\")\"),mdx(\"span\",a({parentName:\"span\"},{className:\"token punctuation\"}),\":\"),`\n`),mdx(\"span\",a({parentName:\"code\"},{className:\"code-line\"}),\"            \",mdx(\"span\",a({parentName:\"span\"},{className:\"token function\"}),\"print\"),mdx(\"span\",a({parentName:\"span\"},{className:\"token punctuation\"}),\"(\"),mdx(\"span\",a({parentName:\"span\"},{className:\"token string\"}),'\"Load level\"'),mdx(\"span\",a({parentName:\"span\"},{className:\"token punctuation\"}),\",\"),\" levels\",mdx(\"span\",a({parentName:\"span\"},{className:\"token punctuation\"}),\"[\"),\"current_level\",mdx(\"span\",a({parentName:\"span\"},{className:\"token punctuation\"}),\"]\"),mdx(\"span\",a({parentName:\"span\"},{className:\"token punctuation\"}),\")\"),`\n`),mdx(\"span\",a({parentName:\"code\"},{className:\"code-line\"}),\"            \",mdx(\"span\",a({parentName:\"span\"},{className:\"token function\"}),\"get_tree\"),mdx(\"span\",a({parentName:\"span\"},{className:\"token punctuation\"}),\"(\"),mdx(\"span\",a({parentName:\"span\"},{className:\"token punctuation\"}),\")\"),mdx(\"span\",a({parentName:\"span\"},{className:\"token punctuation\"}),\".\"),mdx(\"span\",a({parentName:\"span\"},{className:\"token function\"}),\"change_scene\"),mdx(\"span\",a({parentName:\"span\"},{className:\"token punctuation\"}),\"(\"),\"levels\",mdx(\"span\",a({parentName:\"span\"},{className:\"token punctuation\"}),\"[\"),\"current_level\",mdx(\"span\",a({parentName:\"span\"},{className:\"token punctuation\"}),\"]\"),mdx(\"span\",a({parentName:\"span\"},{className:\"token punctuation\"}),\")\"),`\n`))),mdx(\"p\",null,\"Here we have an array of Levels, and as soon as the Ball enters the victory zone, we load the next level.\"),mdx(\"p\",null,'Now all you need is to make more levels. Save the copy of \"Level01\" scene as \"Level02\", and modify it to create a new level. Rename the root node from \"Level01\" to \"Level02\", and use the GridMap node to build a new level.'),mdx(\"p\",null,'Notice that the root nodes of the levels (Level01, Level02, etc, all the ones that have \"Level.gd\" script attached to them) have the \"Current Level\" property in the Inspector panel:'),mdx(\"p\",null,mdx(\"img\",a({parentName:\"p\"},{src:\"/illustrations/lets-roll/20-current-level-variable.png\",alt:null}))),mdx(\"p\",null,\"That's because the line \",mdx(\"inlineCode\",{parentName:\"p\"},\"export var current_level = 0\"),\" exported this variable and made it available in the Inspector panel. Level numbers start at 0, so in Level01 you'll want to set it to 0, in Level02 you'll set it to 1, and so on. That's how our script knows what level we're currently at, and at the line \",mdx(\"inlineCode\",{parentName:\"p\"},\"current_level += 1\"),\" it will increase this value by \",mdx(\"inlineCode\",{parentName:\"p\"},\"1\"),\", so that it can take the next level from the list of levels here: \",mdx(\"inlineCode\",{parentName:\"p\"},\"get_tree().change_scene(levels[current_level])\"),\".\"),mdx(\"p\",null,\"You can make as many levels as you want, and add them all to the array of levels.\"),mdx(\"h2\",a({},{id:\"conclusion\"}),mdx(\"a\",a({parentName:\"h2\"},{className:\"header-link\",href:\"#conclusion\"}),mdx(\"span\",a({parentName:\"a\"},{className:\"icon icon-link\"}))),\"Conclusion\"),mdx(\"p\",null,\"I hope you found this tutorial interesting and useful! If you get stuck or confused while following this tutorial, or have any questions - make a post in our \",mdx(\"a\",a({parentName:\"p\"},{href:\"https://discord.gg/Wbzuk2JP8Y\"}),\"Discord Community\"),\", and I'll help you out. \"),mdx(\"p\",null,\"I'd really appreciate any feedback, it would help me to make the future articles more useful to you. Please leave a \",mdx(\"a\",a({parentName:\"p\"},{href:\"https://www.reddit.com/r/godot/comments/pv11sp/i_wrote_my_first_godot_tutorial_about_making_a/\"}),\"comment\"),\", or feel free to send me an email at \",mdx(\"inlineCode\",{parentName:\"p\"},\"lumenwrites@gmail.com\"),\", or message me on Discord (\",mdx(\"inlineCode\",{parentName:\"p\"},\"lumen#7925\"),\").\"))}MDXContent.isMDXComponent=!0;\n","scope":{"description":"Create your First 3D Game in Godot where the user plays as a bouncing ball.","thumbnail":"/illustrations/lets-roll/thumbnail.png","draft":false,"tags":["3D"]}}},{"title":"Second Tutorial","slug":"second-tutorial","url":"/illustrations/lets-roll/thumbnail.png","tags":[{"name":"3D","slug":"3d"},{"name":"Platformer","slug":"platformer"}],"description":"Different Tutorial","thumbnail":"/illustrations/lets-roll/thumbnail.png","draft":false,"compiledMdx":{"compiledSource":"var f=Object.defineProperty,l=Object.defineProperties;var m=Object.getOwnPropertyDescriptors;var r=Object.getOwnPropertySymbols;var i=Object.prototype.hasOwnProperty,s=Object.prototype.propertyIsEnumerable;var p=(t,a,e)=>a in t?f(t,a,{enumerable:!0,configurable:!0,writable:!0,value:e}):t[a]=e,o=(t,a)=>{for(var e in a||(a={}))i.call(a,e)&&p(t,e,a[e]);if(r)for(var e of r(a))s.call(a,e)&&p(t,e,a[e]);return t},u=(t,a)=>l(t,m(a));var D=typeof require!=\"undefined\"?require:t=>{throw new Error('Dynamic require of \"'+t+'\" is not supported')};var c=(t,a)=>{var e={};for(var n in t)i.call(t,n)&&a.indexOf(n)<0&&(e[n]=t[n]);if(t!=null&&r)for(var n of r(t))a.indexOf(n)<0&&s.call(t,n)&&(e[n]=t[n]);return e};const layoutProps={},MDXLayout=\"wrapper\";function MDXContent(e){var n=e,{components:t}=n,a=c(n,[\"components\"]);return mdx(MDXLayout,u(o(o({},layoutProps),a),{components:t,mdxType:\"MDXLayout\"}),mdx(\"h1\",o({},{id:\"different-tutorial\"}),mdx(\"a\",o({parentName:\"h1\"},{className:\"header-link\",href:\"#different-tutorial\"}),mdx(\"span\",o({parentName:\"a\"},{className:\"icon icon-link\"}))),\"Different Tutorial\"))}MDXContent.isMDXComponent=!0;\n","scope":{"description":"Different Tutorial","thumbnail":"/illustrations/lets-roll/thumbnail.png","draft":false,"tags":["3D","Platformer"],"directLink":"/illustrations/lets-roll/thumbnail.png"}}},{"title":"Wild Rat Chase","slug":"wild-rat-chase","url":"/post/wild-rat-chase","tags":[],"description":"In this adventure the players will meet the King who has been turned into a rat by his evil Vizier. They will need to overcome Viziers minions and reach the highest floor of Vizier's magical tower to acquire the wand that can turn the King back into a human.","thumbnail":"/illustrations/wild-rat-chase/dreamland.jpg","draft":false,"compiledMdx":{"compiledSource":"var u=Object.defineProperty,c=Object.defineProperties;var m=Object.getOwnPropertyDescriptors;var i=Object.getOwnPropertySymbols;var s=Object.prototype.hasOwnProperty,r=Object.prototype.propertyIsEnumerable;var l=(t,a,o)=>a in t?u(t,a,{enumerable:!0,configurable:!0,writable:!0,value:o}):t[a]=o,e=(t,a)=>{for(var o in a||(a={}))s.call(a,o)&&l(t,o,a[o]);if(i)for(var o of i(a))r.call(a,o)&&l(t,o,a[o]);return t},h=(t,a)=>c(t,m(a));var d=typeof require!=\"undefined\"?require:t=>{throw new Error('Dynamic require of \"'+t+'\" is not supported')};var p=(t,a)=>{var o={};for(var n in t)s.call(t,n)&&a.indexOf(n)<0&&(o[n]=t[n]);if(t!=null&&i)for(var n of i(t))a.indexOf(n)<0&&r.call(t,n)&&(o[n]=t[n]);return o};const layoutProps={},MDXLayout=\"wrapper\";function MDXContent(o){var n=o,{components:t}=n,a=p(n,[\"components\"]);return mdx(MDXLayout,h(e(e({},layoutProps),a),{components:t,mdxType:\"MDXLayout\"}),mdx(\"h1\",e({},{id:\"wild-rat-chase\"}),mdx(\"a\",e({parentName:\"h1\"},{className:\"header-link\",href:\"#wild-rat-chase\"}),mdx(\"span\",e({parentName:\"a\"},{className:\"icon icon-link\"}))),\"Wild Rat Chase\"),mdx(\"h2\",e({},{id:\"summary\"}),mdx(\"a\",e({parentName:\"h2\"},{className:\"header-link\",href:\"#summary\"}),mdx(\"span\",e({parentName:\"a\"},{className:\"icon icon-link\"}))),\"Summary\"),mdx(\"p\",null,\"In this adventure the players will meet a King who has been turned into a rat by his evil Vizier. They will need to reach the highest floor of Vizier's magical tower to acquire the magic wand that can turn the King back into a human. They will need to overcome Vizier\\u2019s minions and magical traps of his tower.\"),mdx(\"h2\",e({},{id:\"outline\"}),mdx(\"a\",e({parentName:\"h2\"},{className:\"header-link\",href:\"#outline\"}),mdx(\"span\",e({parentName:\"a\"},{className:\"icon icon-link\"}))),\"Outline\"),mdx(\"ul\",null,mdx(\"li\",{parentName:\"ul\"},\"Characters \",mdx(\"strong\",{parentName:\"li\"},\"meet the rat\"),\" that gives them the scroll of Speak With Animals, explains the situation, and asks them for help.\"),mdx(\"li\",{parentName:\"ul\"},\"They \",mdx(\"strong\",{parentName:\"li\"},\"meet Vizier\\u2019s minions\"),\" who have been chasing the rat.\"),mdx(\"li\",{parentName:\"ul\"},\"They make their way through \",mdx(\"strong\",{parentName:\"li\"},\"the city streets\"),\" to the castle (where the Vizier\\u2019s tower is).\"),mdx(\"li\",{parentName:\"ul\"},\"They find a way through the guarded \",mdx(\"strong\",{parentName:\"li\"},\"castle\\u2019s gates\"),\", or hidden \",mdx(\"strong\",{parentName:\"li\"},\"catacombs\"),\".\"),mdx(\"li\",{parentName:\"ul\"},\"They make their way through the \",mdx(\"strong\",{parentName:\"li\"},\"floors of the tower\"),\" (filled with magical traps).\"),mdx(\"li\",{parentName:\"ul\"},\"They \",mdx(\"strong\",{parentName:\"li\"},\"turn the King back into a human\"),\", and \",mdx(\"strong\",{parentName:\"li\"},\"confront the Vizier\"),\".\"),mdx(\"li\",{parentName:\"ul\"},\"They \",mdx(\"strong\",{parentName:\"li\"},\"receive rewards\"),\" from the King, and \",mdx(\"strong\",{parentName:\"li\"},\"decide the fate of the Vizier\"),\".\")),mdx(\"h2\",e({},{id:\"introducing-characters\"}),mdx(\"a\",e({parentName:\"h2\"},{className:\"header-link\",href:\"#introducing-characters\"}),mdx(\"span\",e({parentName:\"a\"},{className:\"icon icon-link\"}))),\"Introducing Characters\"),mdx(\"p\",null,mdx(\"img\",e({parentName:\"p\"},{src:\"/illustrations/wild-rat-chase/illustrations/ship.jpg\",alt:null}))),mdx(\"p\",null,\"The players begin on a ship, about to arrive at the port.\"),mdx(\"blockquote\",null,mdx(\"p\",{parentName:\"blockquote\"},\"You have been sailing for several weeks now, your course is Cypress, the capital of Anglecynn, the biggest city on the whole continent. At this point you\\u2019re so tired of the ocean, you sincerely hope to never see a drop of water again in your life. Luckily, today is supposed to be the last day of your travels, you\\u2019re about to arrive.\")),mdx(\"blockquote\",null,mdx(\"p\",{parentName:\"blockquote\"},\"You're sitting at an old grimy table, on a middle deck of a ship, waiting for the miserable journey to end.  A piratey-looking sailor, with eyepatches on both of his eyes, comes up to you, pours himself a mug full of rum, and drinks it down in one gulp, and asks \\u201C: \\u201CWhat brings you to Cypress, mateys? And what do you look like? I'm really out of the loop here.\\u201D He points, sadly, at his eyepatches.\")),mdx(\"blockquote\",null,mdx(\"p\",{parentName:\"blockquote\"},\"(It\\u2019s time to introduce your characters)\")),mdx(\"h2\",e({},{id:\"we-see-land\"}),mdx(\"a\",e({parentName:\"h2\"},{className:\"header-link\",href:\"#we-see-land\"}),mdx(\"span\",e({parentName:\"a\"},{className:\"icon icon-link\"}))),\"We see land!\"),mdx(\"p\",null,\"Sailors notice the land, we're about to arrive:\"),mdx(\"blockquote\",null,mdx(\"p\",{parentName:\"blockquote\"},\"As your conversation continues, suddenly you hear the voice from the upper deck \\u201CLand! We've made it! Thank the gods!\\u201D You weren't sure you would, successfully sailing to your destination in the medieval times is always a coin toss. You hear many excited voices and commotion from the upper deck.\")),mdx(\"p\",null,\"Prompt the players to go up to the upper deck and take a look:\"),mdx(\"blockquote\",null,mdx(\"p\",{parentName:\"blockquote\"},`The sailor stands up from the table \"Alright, mateys, I'll go up, take a loo...\" he cuts himself off, \"Smell some fresh air, I guess\" he finishes sadly. \"Follow me if you wish to see the City in all of its glory\"`)),mdx(\"h3\",e({},{id:\"arriving-into-the-port\"}),mdx(\"a\",e({parentName:\"h3\"},{className:\"header-link\",href:\"#arriving-into-the-port\"}),mdx(\"span\",e({parentName:\"a\"},{className:\"icon icon-link\"}))),\"Arriving into the Port\"),mdx(\"p\",null,mdx(\"img\",e({parentName:\"p\"},{src:\"/illustrations/wild-rat-chase/illustrations/02_Dreamland.jpg\",alt:null}))),mdx(\"p\",null,\"Description of Cypress:\"),mdx(\"blockquote\",null,mdx(\"p\",{parentName:\"blockquote\"},\"You walk up to the top deck of the ship, look ahead, and behold the glorious city of Cypress. A huge castle with white walls at the top of the cliff, and the city surrounding it. The city looks quite a bit scruffier than the castle, but it\\u2019s the most impressive one you\\u2019ve seen so far. Soon enough, your ship will arrive and dock in the bay.\")),mdx(\"p\",null,\"Description of the Port:\"),mdx(\"blockquote\",null,mdx(\"p\",{parentName:\"blockquote\"},\"You arrive at the port, the ship docks, and you finally feel the firm ground underneath your feet. You see many sailors running down the gangway onto the bustling boardwalk. Some of them drop on their knees, crying, kissing the earth. It\\u2019s been a long time for these dudes. Many ships are in this port, people are walking around, delivering cargo to and from the ships, selling their wares.\")),mdx(\"h2\",e({},{id:\"meeting-the-rat\"}),mdx(\"a\",e({parentName:\"h2\"},{className:\"header-link\",href:\"#meeting-the-rat\"}),mdx(\"span\",e({parentName:\"a\"},{className:\"icon icon-link\"}))),\"Meeting the Rat\"),mdx(\"div\",{className:\"token\"},mdx(\"img\",{src:\"/illustrations/wild-rat-chase/tokens/rat.png\"})),mdx(\"p\",null,\"Players encounter the rat:\"),mdx(\"blockquote\",null,mdx(\"p\",{parentName:\"blockquote\"},`Amid all the hustle-and-bustle, you notice something very unusual - a fat ginger rat is scurrying directly towards you. It's noticeably distressed. In it's little teeth, it's carrying a scroll. You hear agitated squeaks. \"Squeak squeak squeak!\"`)),mdx(\"p\",null,\"Players read the scroll:\"),mdx(\"blockquote\",null,mdx(\"p\",{parentName:\"blockquote\"},\"It drops a scroll into your hand. You determine it to be a scroll outlining a spell \\u201CSpeak with Animals.\\u201D Whoever touches it and reads it, shall gain the ability to speak to any animal for an hour. Works on multiple people.\")),mdx(\"h3\",e({},{id:\"rats-story\"}),mdx(\"a\",e({parentName:\"h3\"},{className:\"header-link\",href:\"#rats-story\"}),mdx(\"span\",e({parentName:\"a\"},{className:\"icon icon-link\"}))),\"Rat's Story\"),mdx(\"p\",null,\"The Rat tells players it's story. The King turns out to a bit of a self-important condescending impatient jerk, but still sympathetic enough to be worth helping (or he promises players much gold and favors).\"),mdx(\"blockquote\",null,mdx(\"p\",{parentName:\"blockquote\"},\"Once the spell is complete, you hear the Rat's frantic squeaking turns into comprehensible speech:\"),mdx(\"ul\",{parentName:\"blockquote\"},mdx(\"li\",{parentName:\"ul\"},\"\\u201C...to you! Come on! Just read the damn scro\\u2026\\u201D the rat notices changes in your expression \\u201CCan you\\u2026 Can you understand me now? Finally!\\u201D\"),mdx(\"li\",{parentName:\"ul\"},\"Don't you see? Don't you get what is going on? Traitors! Backstabbers! Charlatans!\"),mdx(\"li\",{parentName:\"ul\"},\"What am I? What am I? I'm the king of this bloody kingdom, that's who I am!! And you must help me! You're the only ones who can.\"),mdx(\"li\",{parentName:\"ul\"},\"My vizier, Jafar, the treacherous bastard, has turned me into a rat and he's currently sitting on my throne ruling my kingdom! Consolidating power.\"),mdx(\"li\",{parentName:\"ul\"},\"You must help me retrieve his wand of transfiguration, that's the only way to turn me back. He keeps it in his tower, the tower is in the castle.\"))),mdx(\"h2\",e({},{id:\"meeting-the-minions\"}),mdx(\"a\",e({parentName:\"h2\"},{className:\"header-link\",href:\"#meeting-the-minions\"}),mdx(\"span\",e({parentName:\"a\"},{className:\"icon icon-link\"}))),\"Meeting the Minions\"),mdx(\"h3\",e({},{id:\"zug\"}),mdx(\"a\",e({parentName:\"h3\"},{className:\"header-link\",href:\"#zug\"}),mdx(\"span\",e({parentName:\"a\"},{className:\"icon icon-link\"}))),\"Zug\"),mdx(\"div\",{className:\"token\"},mdx(\"img\",{src:\"/illustrations/wild-rat-chase/tokens/guz.png\"})),mdx(\"p\",null,\"Zug is a half-orc that was tasked with guarding the rat, and he's now really woried he'll be in trouble because the rat has escaped. He's simple but loyal (think Kronk from The Emperor's New Groove).\"),mdx(\"blockquote\",null,mdx(\"p\",{parentName:\"blockquote\"},`The rat is interrupted, and looks back behind it. \"Oh no they're here!\"`)),mdx(\"blockquote\",null,mdx(\"p\",{parentName:\"blockquote\"},\"You feel the earth underneath your feet slightly tremble and hear thud-thud-thud of heavy footsteps. You see a huge figure of a half-orc running towards you, his eyes locked on the rat. \")),mdx(\"blockquote\",null,mdx(\"p\",{parentName:\"blockquote\"},\"The first thing you notice about him is his huge heap of beautiful brown hair, it's like, what shampoo is this guy using to make it so magnificent? Anyway, the second thing is a huge club in his hand that half the size of your body. It seems to have a few blood stains and someone's teeth stuck to it. He stops a few paces away from you, panting, looks around, and notices the rat.\")),mdx(\"p\",null,\"Zug will do his best to negotiate with the players, but if he senses it's not working he'll skip to violence:\"),mdx(\"blockquote\",null,mdx(\"ul\",{parentName:\"blockquote\"},mdx(\"li\",{parentName:\"ul\"},\"Um... Hello... I am, uh, Zug. This rat belongs to the Master, please step aside, I'll go ahead and take it back now.\"),mdx(\"li\",{parentName:\"ul\"},\"Zug will be in so much trouble.\"),mdx(\"li\",{parentName:\"ul\"},\"It is of great sent-ee-mental value to the Master. Negoni, netogi, negonitate!\"),mdx(\"li\",{parentName:\"ul\"},\"I must get it, you see, Mr Jafar told me to guard it, Zug will be in so much trouble if he finds out it escaped.\"))),mdx(\"p\",null,\"Players can fight him, or fool him, or even befriend him.\"),mdx(\"h3\",e({},{id:\"gretchen\"}),mdx(\"a\",e({parentName:\"h3\"},{className:\"header-link\",href:\"#gretchen\"}),mdx(\"span\",e({parentName:\"a\"},{className:\"icon icon-link\"}))),\"Gretchen\"),mdx(\"div\",{className:\"token\"},mdx(\"img\",{src:\"/illustrations/wild-rat-chase/tokens/gretchen.png\"})),mdx(\"p\",null,\"Angry old Hag, Jafar's main minion/partner. They both have blackmail on each other and they both owe favors to each other. She was the one who has found the wand and helped Jafar to execute his plan. Now she'll stop at nothing to get the King back. She's frail but really smart. (Izma from The Emperor's New Groove).\"),mdx(\"blockquote\",null,mdx(\"p\",{parentName:\"blockquote\"},\"You see an old woman catching up with Guz. And when I say old I mean fucking OLD, like she was born before calcium was invented. She is surprisingly spry though.\"),mdx(\"ul\",{parentName:\"blockquote\"},mdx(\"li\",{parentName:\"ul\"},`Guz! What the hell are you doing? I'm, uh... I want to get the kin.. I mean rat, but they won't give it.\nSo hit them on the head with a stick and take it!\nI was trying the, uh, diplomacy.\nJust get the rat you idiot!\nOkay\\u2026`),mdx(\"li\",{parentName:\"ul\"},\"Pazuzu! Where the hell are you, you useless animal! Get the rat, get the rat!\"),mdx(\"li\",{parentName:\"ul\"},\"You kids, give me the rat! I don\\u2019t have time for your nonsense.\"))),mdx(\"h3\",e({},{id:\"pazuzu\"}),mdx(\"a\",e({parentName:\"h3\"},{className:\"header-link\",href:\"#pazuzu\"}),mdx(\"span\",e({parentName:\"a\"},{className:\"icon icon-link\"}))),\"Pazuzu\"),mdx(\"div\",{className:\"token\"},mdx(\"img\",{src:\"/illustrations/wild-rat-chase/tokens/pazuzu.png\"})),mdx(\"p\",null,\"A gargoyle with a difficult personality. He will be circling the skies above the city, making it necessary for players to stay hidden as they make their way to the castle. \"),mdx(\"blockquote\",null,mdx(\"p\",{parentName:\"blockquote\"},\"You see a strange shadow flying high in the atmosphere. Too large for a bird, too small for a blimp. What is it? You have no idea. It circles around, ominously, then begins to descend in the direction of the hag.\")),mdx(\"p\",null,\"If the scene with Zug/Gretchen will take too long, he'll join the battle, try to capture the rat, and return it to the Vizier's tower. If the players escape before this happens, or defend the rat, the rat will be able to help them find the castle, give them tips, tell them about secret catacombs. Otherwise they'll need to make it to the tower on their own, and resquie a rat along with the wand.\"),mdx(\"h2\",e({},{id:\"cypress\"}),mdx(\"a\",e({parentName:\"h2\"},{className:\"header-link\",href:\"#cypress\"}),mdx(\"span\",e({parentName:\"a\"},{className:\"icon icon-link\"}))),\"Cypress\"),mdx(\"p\",null,\"The rat will tell the players which way to go, the biggest challenge is to get through the city unseen from the sky.\"),mdx(\"h3\",e({},{id:\"city-streets\"}),mdx(\"a\",e({parentName:\"h3\"},{className:\"header-link\",href:\"#city-streets\"}),mdx(\"span\",e({parentName:\"a\"},{className:\"icon icon-link\"}))),\"City Streets\"),mdx(\"p\",null,mdx(\"img\",e({parentName:\"p\"},{src:\"/illustrations/wild-rat-chase/illustrations/03_city-streets.jpg\",alt:null}))),mdx(\"p\",null,\"City streets are pretty unremarkable:\"),mdx(\"blockquote\",null,mdx(\"p\",{parentName:\"blockquote\"},\"People are bustling around, going by their daily business.\")),mdx(\"p\",null,\"Players can find a magic item shop, weapons shop, potions shops, a tavern.\"),mdx(\"h3\",e({},{id:\"town-square\"}),mdx(\"a\",e({parentName:\"h3\"},{className:\"header-link\",href:\"#town-square\"}),mdx(\"span\",e({parentName:\"a\"},{className:\"icon icon-link\"}))),\"Town Square\"),mdx(\"p\",null,mdx(\"img\",e({parentName:\"p\"},{src:\"/illustrations/wild-rat-chase/illustrations/04-city-center.jpg\",alt:null}))),mdx(\"p\",null,\"Players arrive at the city center. To reach the gates(or catacombs) they have to cross a wide open area not covered by buildings, without being seen from the sky.\"),mdx(\"blockquote\",null,mdx(\"p\",{parentName:\"blockquote\"},\"You arrive at the town square. You see the castle gate in the distance. \")),mdx(\"h3\",e({},{id:\"city-gates\"}),mdx(\"a\",e({parentName:\"h3\"},{className:\"header-link\",href:\"#city-gates\"}),mdx(\"span\",e({parentName:\"a\"},{className:\"icon icon-link\"}))),\"City Gates\"),mdx(\"p\",null,\"City gates are heavily guarded. Players will have to somehow sneak or talk their way through the guards(it looks like fighting through them is not something players can survive)\"),mdx(\"blockquote\",null,mdx(\"p\",{parentName:\"blockquote\"},`The draw bridge is down, but the gate is guarded by two guards.\nGuards:`),mdx(\"ul\",{parentName:\"blockquote\"},mdx(\"li\",{parentName:\"ul\"},\"Stop right there! State your business!\"))),mdx(\"p\",null,\"If the players tell the truth:\"),mdx(\"blockquote\",null,mdx(\"p\",{parentName:\"blockquote\"},\"One guard turns to another one:\"),mdx(\"ul\",{parentName:\"blockquote\"},mdx(\"li\",{parentName:\"ul\"},\"That is the stupidest lie I have ever heard, huh, bobby\"),mdx(\"li\",{parentName:\"ul\"},\"No doubt.\"))),mdx(\"h3\",e({},{id:\"gunther\"}),mdx(\"a\",e({parentName:\"h3\"},{className:\"header-link\",href:\"#gunther\"}),mdx(\"span\",e({parentName:\"a\"},{className:\"icon icon-link\"}))),\"Gunther\"),mdx(\"p\",null,\"If the players are really stuck, they'll see a peasant name Gunther giving them a look. He will offer to sneak them through the gates inside one of the barrels he's delivering for the feast, as long as they give him a very valuable item, and name their first born after him.\"),mdx(\"blockquote\",null,mdx(\"p\",{parentName:\"blockquote\"},`You notice one of the peasants is trying to look like he's just minding his own business, but his eyes actually dart at you, he seems to be observing you.\nHey fellas. I'm Gunther. I see you want to get into the castle. I can help cha, I can sneak you in my cart, inside the barrels. But it'll cost cha. `)),mdx(\"h3\",e({},{id:\"catacombs\"}),mdx(\"a\",e({parentName:\"h3\"},{className:\"header-link\",href:\"#catacombs\"}),mdx(\"span\",e({parentName:\"a\"},{className:\"icon icon-link\"}))),\"Catacombs\"),mdx(\"p\",null,\"The king may tell the players about the secret passege to the castle through the catacombs, if they ask. There's a door to the catacombs underneath the bridge. The door is locked. Inside the catacombs it's dark, and if you feel like adding an extra challenge, there can be a pack of dog-sized rats with glowing eyes. Also, one of the tunnels may have collapsed, and the players may need to move heavy stones out of the way.\"),mdx(\"blockquote\",null,mdx(\"p\",{parentName:\"blockquote\"},\"You see small points of light glowing in the dark. As you come closer, you see it\\u2019s the eyes of a bunch of mean looking dog-sized rats.\")),mdx(\"h2\",e({},{id:\"tower\"}),mdx(\"a\",e({parentName:\"h2\"},{className:\"header-link\",href:\"#tower\"}),mdx(\"span\",e({parentName:\"a\"},{className:\"icon icon-link\"}))),\"Tower\"),mdx(\"div\",{className:\"token\"},mdx(\"img\",{src:\"/illustrations/wild-rat-chase/illustrations/05-wizard-tower-1.png\"})),mdx(\"p\",null,\"After players make their way through the catacombs or through the gate, they see Jafar's tower:\"),mdx(\"blockquote\",null,mdx(\"p\",{parentName:\"blockquote\"},\"You enter a castle, and have no trouble noticing a tall, slender, magnificent tower that is, well, towering over you.\")),mdx(\"h3\",e({},{id:\"tower-entrance\"}),mdx(\"a\",e({parentName:\"h3\"},{className:\"header-link\",href:\"#tower-entrance\"}),mdx(\"span\",e({parentName:\"a\"},{className:\"icon icon-link\"}))),\"Tower Entrance\"),mdx(\"p\",null,\"The only way into the tower is through the giant metal gates. They are sealed by magic, they have no obvious lock, but they have a handle in the shape of a snake, and a bell.\"),mdx(\"p\",null,mdx(\"strong\",{parentName:\"p\"},\"Snake Handle\")),mdx(\"blockquote\",null,mdx(\"p\",{parentName:\"blockquote\"},`You see a door handle in a shape of a snake. Small emerald eyes reflect the sky, making it seem almost alive.\nIf the player touches the snake handle, it comes alive and bites them. Now they're poisoned, and will lose one HP per minute, until they find the antidote (Laboratory in the tower has a lot of potions).`)),mdx(\"p\",null,mdx(\"strong\",{parentName:\"p\"},\"Door Bell\")),mdx(\"p\",null,\"Door bell answers in an autoresponder voice and lets them in:\"),mdx(\"blockquote\",null,mdx(\"p\",{parentName:\"blockquote\"},'Say \"One\" if you dare to request an audience with the Vizier. Say \"Two\" if you come bearing gifts for his lordship. Say \"Three\" if you feel unworthy to even be in his presence. Say \"Four\" if you and would like to take this opportunity to walk away before incurring his wrath. Say \"Five\" if you would like to proceed against your better judgement.')),mdx(\"h3\",e({},{id:\"reception\"}),mdx(\"a\",e({parentName:\"h3\"},{className:\"header-link\",href:\"#reception\"}),mdx(\"span\",e({parentName:\"a\"},{className:\"icon icon-link\"}))),\"Reception\"),mdx(\"p\",null,\"The first floor has a receptionist (clay golem) sitting in the middle behind the table. Next to the walls are 5 large empty suits of armor - the security system. If the receptionist feels threatened, they can activate them, making them come alive and attack the players.\"),mdx(\"blockquote\",null,mdx(\"p\",{parentName:\"blockquote\"},`The room seems unnaturally enormous, way larger than the tower looks from the outside. You see a square table, and behind it a small clay golem. It seems to be polishing it\\u2019s nails and staring at a small hand-held mirror, talking to someone on the other side \"And I told him, not today mister. And then he was like, I don't care. And I was like, ugh, You know what I mean?\"`)),mdx(\"p\",null,\"The receptionist will ask them if they have an appointment, and check it's records to see if what they're saying is true. Players can try lying, using illusions, or subduing it before it can trigger the alarm.\"),mdx(\"p\",null,\"After receptionist has been dealt with, the players can go up to the next floor by using the staircase.\"),mdx(\"h3\",e({},{id:\"the-office\"}),mdx(\"a\",e({parentName:\"h3\"},{className:\"header-link\",href:\"#the-office\"}),mdx(\"span\",e({parentName:\"a\"},{className:\"icon icon-link\"}))),\"The Office\"),mdx(\"p\",null,mdx(\"img\",e({parentName:\"p\"},{src:\"/illustrations/wild-rat-chase/illustrations/the-office.jpg\",alt:null}))),mdx(\"p\",null,\"The second floor of the tower is the Vizier's office:\"),mdx(\"blockquote\",null,mdx(\"p\",{parentName:\"blockquote\"},`The room looks like the office where he holds political meetings. It has a large desk in the center, papers, all neat and tidy. A crystal globe standing off to the side.\nThere's a portrait of a man with big mustache on the wall, his eyes, and his moustache, seem to follow them wherever they move. A set of diplomas and impressive looking papers hang around the painting. \\u201CMost Creative Use Of A Bigby\\u2019s Hand Spell\\u201D, \\u201CIn recognition of contributions to the Most Noble Art of Conjuration\\u201D,  \\u201CGraduate of the Arcane Arts at Samadar\\u2019s School For Gifted Youths\\u201D. Portrait, crystal on his desk.`)),mdx(\"p\",null,\"If a player decides to activate the crystal (by touching it and funneling 1 point of energy into it), they will see a vision of many things, among them - the location of the wand and Vizier sitting on the throne:\"),mdx(\"blockquote\",null,mdx(\"p\",{parentName:\"blockquote\"},\"When you touch the crystal, the time and space unfold in front of his vision. He sees flashes of images. A giant empty cathedral. A dragon sleeping on a pile of gold. A round room with a desk, somewhere high above, with a glowing rod laying among it's contents. A vampire drinking blood from the neck of a young maiden. A tall slender man sitting on a throne. A city the likes of which you've never seen, gleaming with light, with buildings as tall as the sky, horseless carriages driving back and forth on the straight lines of it's roads. A giant tentacled creature dwelling in the depths of the ocean. An old man playing fetch with his dog.\")),mdx(\"h3\",e({},{id:\"the-laboratory\"}),mdx(\"a\",e({parentName:\"h3\"},{className:\"header-link\",href:\"#the-laboratory\"}),mdx(\"span\",e({parentName:\"a\"},{className:\"icon icon-link\"}))),\"The Laboratory\"),mdx(\"p\",null,\"The next floor is Vizier's laboratory.\"),mdx(\"blockquote\",null,mdx(\"p\",{parentName:\"blockquote\"},\"It looks like a study, or a laboratory. A desk filled with vials and bubbling potions(unlabeled). A pentagram on the floor, with a tiny demon-like creature sitting in the middle, looking bored. A small cage with an ordinary looking coffee table sitting inside it, whimpering pitifully.\")),mdx(\"p\",null,\"If the players decide to open the cage with the animated coffee table - it will happily run off to it's freedom. If they interact with the demon-like creature, it will say something mean in the language they don't undersand, show them a rude gesture, and get back to looking bored.\"),mdx(\"p\",null,\"One of the potions contains the antidote to the snake handle's venom, but potions are unlabeled. Drinking them randomly will produce random effects - reversing the gravity for the player, making them hallucinate, making them fall in love with whatever they're looking at, etc.\"),mdx(\"h3\",e({},{id:\"the-observatory\"}),mdx(\"a\",e({parentName:\"h3\"},{className:\"header-link\",href:\"#the-observatory\"}),mdx(\"span\",e({parentName:\"a\"},{className:\"icon icon-link\"}))),\"The Observatory\"),mdx(\"p\",null,mdx(\"img\",e({parentName:\"p\"},{src:\"/illustrations/wild-rat-chase/illustrations/observatory.jpg\",alt:null}))),mdx(\"p\",null,\"The next room is where Vizier studies parallel dimensions:\"),mdx(\"blockquote\",null,mdx(\"p\",{parentName:\"blockquote\"},\"There\\u2019s a huge telescope in the middle of the room, maps of the starlit sky, and what looks like a model of some kind of planetary system. The room is illuminated by ominous rays of red light streaming from the window.\")),mdx(\"p\",null,\"If the players look out of the window, they'll see:\"),mdx(\"blockquote\",null,mdx(\"p\",{parentName:\"blockquote\"},\"As you pass by the window, you inadvertently see a deep blue sky, above the dark red ocean. Three red moons illuminate the strange scene.\")),mdx(\"p\",null,\"When a player steps into the red light:\"),mdx(\"blockquote\",null,mdx(\"p\",{parentName:\"blockquote\"},\"You feel something deep inside of you awaken, the primal rage, the thirst for blood. You look at your companions. Why have you never thought your companions would make for a good breakfast?\")),mdx(\"p\",null,\"The window can be blocked by something opaque.\"),mdx(\"h3\",e({},{id:\"top-floor\"}),mdx(\"a\",e({parentName:\"h3\"},{className:\"header-link\",href:\"#top-floor\"}),mdx(\"span\",e({parentName:\"a\"},{className:\"icon icon-link\"}))),\"Top Floor\"),mdx(\"p\",null,\"At the top floor the players will find the desk with a wand laying on top of it:\"),mdx(\"blockquote\",null,mdx(\"p\",{parentName:\"blockquote\"},\"On the table nearby you see a rod you saw in your vision. The rod emits green light and a quiet humming sound. Once you take it, you feel mighty and powerful, like anything in the world could be reshaped according to your will. You hear the whale of an alarm, and soon, footsteps from the lower floors of the tower.\")),mdx(\"p\",null,\"In the middle of the room is the portal gate:\"),mdx(\"blockquote\",null,mdx(\"p\",{parentName:\"blockquote\"},\"In the center of the room you see a large obsidian circle, large enough to walk through, standing vertically on a pitch black pedestal. It looks like a strange gate.\")),mdx(\"h2\",e({},{id:\"transforming-the-king\"}),mdx(\"a\",e({parentName:\"h2\"},{className:\"header-link\",href:\"#transforming-the-king\"}),mdx(\"span\",e({parentName:\"a\"},{className:\"icon icon-link\"}))),\"Transforming the King\"),mdx(\"div\",{className:\"token\"},mdx(\"img\",{src:\"/illustrations/wild-rat-chase/tokens/king.png\"})),mdx(\"p\",null,\"When the rat sees the wand:\"),mdx(\"blockquote\",null,mdx(\"p\",{parentName:\"blockquote\"},\"The Rat jumps up and down on your shoulder, forgetting any shreds of the kingly dignity it had left, unable to contain it's excitement.\")),mdx(\"p\",null,\"When a player activates the wand to transform the rat:\"),mdx(\"blockquote\",null,mdx(\"p\",{parentName:\"blockquote\"},`With the sound of thunder and lightning, the room fills with the blazing green light. Streams of mana and energy surround the Rat in a blinding whirlwind of light and power. You can barely see the shape of the Rat growing, changing. Surprised squeaks gradually lower in pitch, becoming shrieks and then grunts of a human.\nAs the magic and might begin to settle, you behold with your own eyes the majesty of the true king of this kingdom in his natural, human form.`)),mdx(\"h3\",e({},{id:\"throne-room\"}),mdx(\"a\",e({parentName:\"h3\"},{className:\"header-link\",href:\"#throne-room\"}),mdx(\"span\",e({parentName:\"a\"},{className:\"icon icon-link\"}))),\"Throne Room\"),mdx(\"p\",null,mdx(\"img\",e({parentName:\"p\"},{src:\"/illustrations/wild-rat-chase/illustrations/throne-room.jpg\",alt:null}))),mdx(\"p\",null,\"If the players activate the portal gate, it will open a wormhole into the throne room:\"),mdx(\"blockquote\",null,mdx(\"p\",{parentName:\"blockquote\"},\"After you finish your manipulations, the space inside the circle seems to disappear, as if the hole has been torn through the universe, and on the other side, you see the throne room, a tall slender man sitting on the throne, and a few dozen of guards around him.\")),mdx(\"h3\",e({},{id:\"jafar\"}),mdx(\"a\",e({parentName:\"h3\"},{className:\"header-link\",href:\"#jafar\"}),mdx(\"span\",e({parentName:\"a\"},{className:\"icon icon-link\"}))),\"Jafar\"),mdx(\"div\",{className:\"token\"},mdx(\"img\",{src:\"/illustrations/wild-rat-chase/tokens/jafar.png\"})),mdx(\"p\",null,\"Jafar looks surprised and shocked\"),mdx(\"blockquote\",null,mdx(\"p\",{parentName:\"blockquote\"},`\"Your Majesty! I'm so happy to see you again! Everybody, rejoice, the lost king has returned!\"`)),mdx(\"p\",null,\"If by the time players are in the throne room the king is still in the rat form, the guards will follow Vizier's commands, otherwise they will do what the King tells them to.\"),mdx(\"p\",null,\"Vizier will try to talk/grovel his way to King's mercy, or set the guards on players and try to fight them.\"),mdx(\"h3\",e({},{id:\"conclusion-and-rewards\"}),mdx(\"a\",e({parentName:\"h3\"},{className:\"header-link\",href:\"#conclusion-and-rewards\"}),mdx(\"span\",e({parentName:\"a\"},{className:\"icon icon-link\"}))),\"Conclusion and Rewards\"),mdx(\"p\",null,'Once the Vizier has been defeated, the King will attempt to save face and take credit by claiming that it was his \"brilliant leadership\" that has secured this victory, but in the end, will be grateful to the players, and grant each player a request (if they remind him that he owes them).'),mdx(\"blockquote\",null,mdx(\"p\",{parentName:\"blockquote\"},'\"Is the gratitude of the king not enough for you people? Fine!\" The King snaps his fingers in the direction of one of his servants. \"Ignacius, dash to the treasury, fetch us some of the finest ',\"[\",\"whatever players ask\",\"]\",\".\")),mdx(\"hr\",null),mdx(\"p\",null,\"This adventure was made by the \",mdx(\"a\",e({parentName:\"p\"},{href:\"https://rpgadventures.io/writers-room\"}),\"Adventure Writer's Room\"),\" community. We are a group of GMs who meet in the discord voice chat, and challenge ourselves to improvise a one-shot adventure in 2 hours. Our goal is to brainstorm fun ideas and improvise stories together in a chill, lighthearted, no-pressure environment. It works, it really helps with the writing, and it is super fun.\"),mdx(\"p\",null,\"We're looking for some friendly and creative people to join us!\"),mdx(\"hr\",null),mdx(\"p\",null,\"See the playtest of this adventure \",mdx(\"a\",e({parentName:\"p\"},{href:\"https://www.youtube.com/watch?v=Cn9vV_wHpY4\"}),\"here\"),\".\"))}MDXContent.isMDXComponent=!0;\n","scope":{"title":"Wild Rat Chase","description":"In this adventure the players will meet the King who has been turned into a rat by his evil Vizier. They will need to overcome Viziers minions and reach the highest floor of Vizier's magical tower to acquire the wand that can turn the King back into a human.","thumbnail":"/illustrations/wild-rat-chase/dreamland.jpg","draft":false,"tags":[]}}}]